mux2x1_conditional/mux2x1_conditional.v
module mux2x1_conditional(input a, input b, input sel, output res);

	assign res = sel ? b : a;

endmodule

mux2x1_conditional/mux2x1_conditional_tb.v
module mux2x1_conditional_tb();
reg a;
reg b;
reg sel;
integer i=0, j=0;
wire res;

mux2x1_conditional mux2x1_conditional_tb(
	.a(a),
	.b(b),
	.sel(sel),
	.res(res)
);

	initial
		begin
			for(i=0;i<4;i=i+1)
				begin
					for(j=0;j<2;j=j+1)
					begin
						sel=j;
						{a,b} = i;
						#10;
					end
				end
		end

	initial
		begin
			$dumpfile("mux2x1_conditional.vcd");
			$dumpvars(0, mux2x1_conditional_tb);
			$monitor("time = %2d, a = %1b, b = %1b, select = %1b result = %1b", $time, a, b, sel, res);
		end

endmodule

mux2x1_conditional/mux2x1_conditional.vcd
$date
	Thu Sep 27 14:36:03 2018
$end
$version
	Icarus Verilog
$end
$timescale
	1s
$end
$scope module mux2x1_conditional_tb $end
$scope module mux2x1_conditional_tb $end
$var wire 1 ! a $end
$var wire 1 " b $end
$var wire 1 # sel $end
$var wire 1 $ res $end
$upscope $end
$upscope $end
$enddefinitions $end
#0
$dumpvars
0$
0#
0"
0!
$end
#10
1#
#20
1"
0#
#30
1$
1#
#40
1!
0"
0#
#50
0$
1#
#60
1$
1"
0#
#70
1#
