demux1x8_switch/demux1x8_switch.v
module demux1x8_switch(input in, input [2:0]sel, output reg [7:0]result);

always @ *
	begin
		case(sel)
			3'b000: result <= 'h1;
			3'b001: result <= 'h2;
			3'b010: result <= 'h4;
			3'b011: result <= 'h8;
			3'b100: result <= 'h10;
			3'b101: result <= 'h20;
			3'b110: result <= 'h40;
			3'b111: result <= 'h80;
		endcase
	end

endmodule

demux1x8_switch/demux1x8_switch_tb.v
module demux1x8_switch_tb();
reg in;
reg [2:0]sel;
wire [7:0]res;

demux1x8_switch demux1x8_switch_tb(
	.in(in),
	.sel(sel),
	.result(res)
);

	initial
		begin
				 in=1;
				 sel=3'b000;
			#10; sel=3'b001;
			#10; sel=3'b010;
			#10; sel=3'b011;
			#10; sel=3'b100;
			#10; sel=3'b101;
			#10; sel=3'b110;
			#10; sel=3'b111;
		end

	initial
		begin
			$dumpfile("demux1x8_switch.vcd");
			$dumpvars(0, demux1x8_switch_tb);
			$monitor("time = %2d, input = %1b, select = %3b result = %h", $time, in, sel, res);
		end

endmodule

demux1x8_switch/demux1x8_switch.vcd
$date
	Thu Sep 20 15:59:46 2018
$end
$version
	Icarus Verilog
$end
$timescale
	1s
$end
$scope module demux1x8_switch_tb $end
$scope module demux1x8_switch_tb $end
$var wire 1 ! in $end
$var wire 3 " sel [2:0] $end
$var reg 8 # result [7:0] $end
$upscope $end
$upscope $end
$enddefinitions $end
#0
$dumpvars
b1 #
b0 "
1!
$end
#10
b10 #
b1 "
#20
b100 #
b10 "
#30
b1000 #
b11 "
#40
b10000 #
b100 "
#50
b100000 #
b101 "
#60
b1000000 #
b110 "
#70
b10000000 #
b111 "
