not/not.v
module not_gate(input a, output result);

	supply1 Vdd;
	supply0 Gnd;

	pmos(result, Vdd, a);
	nmos(result, Gnd, a);

endmodule

tranmission/tranmission.v
`include "../not/not.v"

module transmission(input a, input en, output result);

	wire en_comp;

	not_gate not_temp(
		.a(en),
		.result(en_comp)
	);
	
	pmos(result, a, en_comp);
	nmos(result, a, en);

endmodule

2x1mux_trans/2x1mux_trans.v
`include "../tranmission/tranmission.v"

module mux_2x1_trans(input d0, input d1, input s, output result);

	wire s_comp;

	not_gate not_temp(
		.a(s),
		.result(s_comp)
	);

	transmission transmission_temp1(
		.a(d0),
		.en(s_comp),
		.result(result)
	);

	transmission transmission_temp2(
		.a(d1),
		.en(s),
		.result(result)
	);

endmodule

4x1mux_trans/4x1mux_trans.v
`include "../2x1mux_trans/2x1mux_trans.v"

module mux_4x1_trans(input d0, input d1, input d2, input d3, input s0, input s1, output result);

	wire mux1;
	wire mux2;
	wire result_temp;

	mux_2x1_trans mux_temp1(
		.d0(d0),
		.d1(d1),
		.s(s0),
		.result(mux1)
	);

	mux_2x1_trans mux_temp2(
		.d0(d2),
		.d1(d3),
		.s(s0),
		.result(mux2)
	);

	mux_2x1_trans mux_temp3(
		.d0(mux1),
		.d1(mux2),
		.s(s1),
		.result(result_temp)
	);

	not_gate not_temp(
		.a(result_temp),
		.result(result)
	);

endmodule

4x1mux_trans/4x1mux_trans_tb.v
module mux_4x1_trans_tb();
reg a;
reg b;
reg c;
reg d;
reg s1;
reg s2;
wire res;

mux_4x1_trans mux_4x1_trans_tb(
	.d0(a),
	.d1(b),
	.d2(c),
	.d3(d),
	.s0(s1),
	.s1(s2),
	.result(res)
);

	initial
		begin
				s2 = 0; s1 = 0; d = 0; c = 0; b = 0; a = 0; 
			#10 s2 = 0; s1 = 0; d = 0; c = 0; b = 0; a = 1; 
			#10 s2 = 0; s1 = 0; d = 0; c = 0; b = 1; a = 0; 
			#10 s2 = 0; s1 = 0; d = 0; c = 0; b = 1; a = 1; 
			#10 s2 = 0; s1 = 0; d = 0; c = 1; b = 0; a = 0; 
			#10 s2 = 0; s1 = 0; d = 0; c = 1; b = 0; a = 1; 
			#10 s2 = 0; s1 = 0; d = 0; c = 1; b = 1; a = 0; 
			#10 s2 = 0; s1 = 0; d = 0; c = 1; b = 1; a = 1; 
			#10 s2 = 0; s1 = 0; d = 1; c = 0; b = 0; a = 0; 
			#10 s2 = 0; s1 = 0; d = 1; c = 0; b = 0; a = 1; 
			#10 s2 = 0; s1 = 0; d = 1; c = 0; b = 1; a = 0; 
			#10 s2 = 0; s1 = 0; d = 1; c = 0; b = 1; a = 1; 
			#10 s2 = 0; s1 = 0; d = 1; c = 1; b = 0; a = 0; 
			#10 s2 = 0; s1 = 0; d = 1; c = 1; b = 0; a = 1; 
			#10 s2 = 0; s1 = 0; d = 1; c = 1; b = 1; a = 0; 
			#10 s2 = 0; s1 = 0; d = 1; c = 1; b = 1; a = 1; 
			#10 s2 = 0; s1 = 1; d = 0; c = 0; b = 0; a = 0; 
			#10 s2 = 0; s1 = 1; d = 0; c = 0; b = 0; a = 1; 
			#10 s2 = 0; s1 = 1; d = 0; c = 0; b = 1; a = 0; 
			#10 s2 = 0; s1 = 1; d = 0; c = 0; b = 1; a = 1; 
			#10 s2 = 0; s1 = 1; d = 0; c = 1; b = 0; a = 0; 
			#10 s2 = 0; s1 = 1; d = 0; c = 1; b = 0; a = 1; 
			#10 s2 = 0; s1 = 1; d = 0; c = 1; b = 1; a = 0; 
			#10 s2 = 0; s1 = 1; d = 0; c = 1; b = 1; a = 1; 
			#10 s2 = 0; s1 = 1; d = 1; c = 0; b = 0; a = 0; 
			#10 s2 = 0; s1 = 1; d = 1; c = 0; b = 0; a = 1; 
			#10 s2 = 0; s1 = 1; d = 1; c = 0; b = 1; a = 0; 
			#10 s2 = 0; s1 = 1; d = 1; c = 0; b = 1; a = 1; 
			#10 s2 = 0; s1 = 1; d = 1; c = 1; b = 0; a = 0; 
			#10 s2 = 0; s1 = 1; d = 1; c = 1; b = 0; a = 1; 
			#10 s2 = 0; s1 = 1; d = 1; c = 1; b = 1; a = 0; 
			#10 s2 = 0; s1 = 1; d = 1; c = 1; b = 1; a = 1; 
			#10 s2 = 1; s1 = 0; d = 0; c = 0; b = 0; a = 0; 
			#10 s2 = 1; s1 = 0; d = 0; c = 0; b = 0; a = 1; 
			#10 s2 = 1; s1 = 0; d = 0; c = 0; b = 1; a = 0; 
			#10 s2 = 1; s1 = 0; d = 0; c = 0; b = 1; a = 1; 
			#10 s2 = 1; s1 = 0; d = 0; c = 1; b = 0; a = 0; 
			#10 s2 = 1; s1 = 0; d = 0; c = 1; b = 0; a = 1; 
			#10 s2 = 1; s1 = 0; d = 0; c = 1; b = 1; a = 0; 
			#10 s2 = 1; s1 = 0; d = 0; c = 1; b = 1; a = 1; 
			#10 s2 = 1; s1 = 0; d = 1; c = 0; b = 0; a = 0; 
			#10 s2 = 1; s1 = 0; d = 1; c = 0; b = 0; a = 1; 
			#10 s2 = 1; s1 = 0; d = 1; c = 0; b = 1; a = 0; 
			#10 s2 = 1; s1 = 0; d = 1; c = 0; b = 1; a = 1; 
			#10 s2 = 1; s1 = 0; d = 1; c = 1; b = 0; a = 0; 
			#10 s2 = 1; s1 = 0; d = 1; c = 1; b = 0; a = 1; 
			#10 s2 = 1; s1 = 0; d = 1; c = 1; b = 1; a = 0; 
			#10 s2 = 1; s1 = 0; d = 1; c = 1; b = 1; a = 1; 
			#10 s2 = 1; s1 = 1; d = 0; c = 0; b = 0; a = 0; 
			#10 s2 = 1; s1 = 1; d = 0; c = 0; b = 0; a = 1; 
			#10 s2 = 1; s1 = 1; d = 0; c = 0; b = 1; a = 0; 
			#10 s2 = 1; s1 = 1; d = 0; c = 0; b = 1; a = 1; 
			#10 s2 = 1; s1 = 1; d = 0; c = 1; b = 0; a = 0; 
			#10 s2 = 1; s1 = 1; d = 0; c = 1; b = 0; a = 1; 
			#10 s2 = 1; s1 = 1; d = 0; c = 1; b = 1; a = 0; 
			#10 s2 = 1; s1 = 1; d = 0; c = 1; b = 1; a = 1; 
			#10 s2 = 1; s1 = 1; d = 1; c = 0; b = 0; a = 0; 
			#10 s2 = 1; s1 = 1; d = 1; c = 0; b = 0; a = 1; 
			#10 s2 = 1; s1 = 1; d = 1; c = 0; b = 1; a = 0; 
			#10 s2 = 1; s1 = 1; d = 1; c = 0; b = 1; a = 1; 
			#10 s2 = 1; s1 = 1; d = 1; c = 1; b = 0; a = 0; 
			#10 s2 = 1; s1 = 1; d = 1; c = 1; b = 0; a = 1; 
			#10 s2 = 1; s1 = 1; d = 1; c = 1; b = 1; a = 0; 
			#10 s2 = 1; s1 = 1; d = 1; c = 1; b = 1; a = 1; 
		end

	initial
		begin
			$dumpfile("mux_4x1_trans.vcd");
			$dumpvars(0, mux_4x1_trans_tb);
			$monitor("time = %2d, abit = %1b, bbit = %1b, cbit = %1b, dbit = %1b, s1bit = %1b, s2bit = %1b, result = %1b", $time, a, b, c, d, s1, s2, res);
		end

endmodule

4x1mux_trans/mux_4x1_trans.vcd
$date
	Thu Sep  6 16:06:28 2018
$end
$version
	Icarus Verilog
$end
$timescale
	1s
$end
$scope module mux_4x1_trans_tb $end
$scope module mux_4x1_trans_tb $end
$var wire 1 ! d0 $end
$var wire 1 " d1 $end
$var wire 1 # d2 $end
$var wire 1 $ d3 $end
$var wire 1 % mux1 $end
$var wire 1 & mux2 $end
$var wire 1 ' result $end
$var wire 1 ( result_temp $end
$var wire 1 ) s0 $end
$var wire 1 * s1 $end
$scope module mux_temp1 $end
$var wire 1 ! d0 $end
$var wire 1 " d1 $end
$var wire 1 % result $end
$var wire 1 ) s $end
$var wire 1 + s_comp $end
$scope module not_temp $end
$var wire 1 , Gnd $end
$var wire 1 - Vdd $end
$var wire 1 ) a $end
$var wire 1 + result $end
$upscope $end
$scope module transmission_temp1 $end
$var wire 1 ! a $end
$var wire 1 + en $end
$var wire 1 . en_comp $end
$var wire 1 % result $end
$scope module not_temp $end
$var wire 1 / Gnd $end
$var wire 1 0 Vdd $end
$var wire 1 + a $end
$var wire 1 . result $end
$upscope $end
$upscope $end
$scope module transmission_temp2 $end
$var wire 1 " a $end
$var wire 1 ) en $end
$var wire 1 1 en_comp $end
$var wire 1 % result $end
$scope module not_temp $end
$var wire 1 2 Gnd $end
$var wire 1 3 Vdd $end
$var wire 1 ) a $end
$var wire 1 1 result $end
$upscope $end
$upscope $end
$upscope $end
$scope module mux_temp2 $end
$var wire 1 # d0 $end
$var wire 1 $ d1 $end
$var wire 1 & result $end
$var wire 1 ) s $end
$var wire 1 4 s_comp $end
$scope module not_temp $end
$var wire 1 5 Gnd $end
$var wire 1 6 Vdd $end
$var wire 1 ) a $end
$var wire 1 4 result $end
$upscope $end
$scope module transmission_temp1 $end
$var wire 1 # a $end
$var wire 1 4 en $end
$var wire 1 7 en_comp $end
$var wire 1 & result $end
$scope module not_temp $end
$var wire 1 8 Gnd $end
$var wire 1 9 Vdd $end
$var wire 1 4 a $end
$var wire 1 7 result $end
$upscope $end
$upscope $end
$scope module transmission_temp2 $end
$var wire 1 $ a $end
$var wire 1 ) en $end
$var wire 1 : en_comp $end
$var wire 1 & result $end
$scope module not_temp $end
$var wire 1 ; Gnd $end
$var wire 1 < Vdd $end
$var wire 1 ) a $end
$var wire 1 : result $end
$upscope $end
$upscope $end
$upscope $end
$scope module mux_temp3 $end
$var wire 1 % d0 $end
$var wire 1 & d1 $end
$var wire 1 ( result $end
$var wire 1 * s $end
$var wire 1 = s_comp $end
$scope module not_temp $end
$var wire 1 > Gnd $end
$var wire 1 ? Vdd $end
$var wire 1 * a $end
$var wire 1 = result $end
$upscope $end
$scope module transmission_temp1 $end
$var wire 1 % a $end
$var wire 1 = en $end
$var wire 1 @ en_comp $end
$var wire 1 ( result $end
$scope module not_temp $end
$var wire 1 A Gnd $end
$var wire 1 B Vdd $end
$var wire 1 = a $end
$var wire 1 @ result $end
$upscope $end
$upscope $end
$scope module transmission_temp2 $end
$var wire 1 & a $end
$var wire 1 * en $end
$var wire 1 C en_comp $end
$var wire 1 ( result $end
$scope module not_temp $end
$var wire 1 D Gnd $end
$var wire 1 E Vdd $end
$var wire 1 * a $end
$var wire 1 C result $end
$upscope $end
$upscope $end
$upscope $end
$scope module not_temp $end
$var wire 1 F Gnd $end
$var wire 1 G Vdd $end
$var wire 1 ( a $end
$var wire 1 ' result $end
$upscope $end
$upscope $end
$upscope $end
$enddefinitions $end
#0
$dumpvars
1G
0F
1E
0D
1C
1B
0A
0@
1?
0>
1=
1<
0;
1:
19
08
07
16
05
14
13
02
11
10
0/
0.
1-
0,
1+
0*
0)
0(
1'
0&
0%
0$
0#
0"
0!
$end
#10
0'
1(
1%
1!
#20
1'
0(
0%
0!
1"
#30
0'
1(
1%
1!
#40
1'
0(
0%
0!
0"
1&
1#
#50
0'
1(
1%
1!
#60
1'
0(
0%
0!
1"
#70
0'
1(
1%
1!
#80
1'
0(
0%
0!
0"
0&
0#
1$
#90
0'
1(
1%
1!
#100
1'
0(
0%
0!
1"
#110
0'
1(
1%
1!
#120
1'
0(
0%
0!
0"
1&
1#
#130
0'
1(
1%
1!
#140
1'
0(
0%
0!
1"
#150
0'
1(
1%
1!
#160
0!
1'
0(
0%
0"
0#
0&
0$
1.
0+
01
17
04
0:
1)
#170
1!
#180
0!
0'
1(
1%
1"
#190
1!
#200
0!
1'
0(
0%
0"
1#
#210
1!
#220
0!
0'
1(
1%
1"
#230
1!
#240
0!
1'
0(
0%
0"
0#
1&
1$
#250
1!
#260
0!
0'
1(
1%
1"
#270
1!
#280
0!
1'
0(
0%
0"
1#
#290
1!
#300
0!
0'
1(
1%
1"
#310
1!
#320
0!
0"
0#
0$
0.
1+
0%
11
07
14
1'
0(
0&
1:
0)
1@
0=
0C
1*
#330
1%
1!
#340
0%
0!
1"
#350
1%
1!
#360
0%
0!
0"
0'
1(
1&
1#
#370
1%
1!
#380
0%
0!
1"
#390
1%
1!
#400
0%
0!
0"
1'
0(
0&
0#
1$
#410
1%
1!
#420
0%
0!
1"
#430
1%
1!
#440
0%
0!
0"
0'
1(
1&
1#
#450
1%
1!
#460
0%
0!
1"
#470
1%
1!
#480
0!
0%
0"
0#
1'
0(
0&
0$
1.
0+
01
17
04
0:
1)
#490
1!
#500
0!
1%
1"
#510
1!
#520
0!
0%
0"
1#
#530
1!
#540
0!
1%
1"
#550
1!
#560
0!
0%
0"
0#
0'
1(
1&
1$
#570
1!
#580
0!
1%
1"
#590
1!
#600
0!
0%
0"
1#
#610
1!
#620
0!
1%
1"
#630
1!
