not/not.v
module not_gate(input a, output result);

	supply1 Vdd;
	supply0 Gnd;

	pmos(result, Vdd, a);
	nmos(result, Gnd, a);

endmodule

tranmission/tranmission.v
`include "../not/not.v"

module transmission(input a, input en, output result);

	wire en_comp;

	not_gate not_temp(
		.a(en),
		.result(en_comp)
	);
	
	pmos(result, a, en_comp);
	nmos(result, a, en);

endmodule

2x1mux_trans/2x1mux_trans.v
`include "../tranmission/tranmission.v"

module mux_2x1_trans(input d0, input d1, input s, output result);

	wire s_comp;

	not_gate not_temp(
		.a(s),
		.result(s_comp)
	);

	transmission transmission_temp1(
		.a(d0),
		.en(s_comp),
		.result(result)
	);

	transmission transmission_temp2(
		.a(d1),
		.en(s),
		.result(result)
	);

endmodule

2x1mux_trans/2x1mux_trans_tb.v
module mux_2x1_trans_tb();
reg abit;
reg bbit;
reg sbit;
wire res;

mux_2x1_trans mux_2x1_trans_tb(
	.d0(abit),
	.d1(bbit),
	.s(sbit),
	.result(res)
);

	initial
		begin
				 sbit=0; bbit=0; abit=0;
			#10; sbit=0; bbit=0; abit=1;
			#10; sbit=0; bbit=1; abit=0;
			#10; sbit=0; bbit=1; abit=1;
			#10; sbit=1; bbit=0; abit=0;
			#10; sbit=1; bbit=0; abit=1;
			#10; sbit=1; bbit=1; abit=0;
			#10; sbit=1; bbit=1; abit=1;
		end

	initial
		begin
			$dumpfile("mux_2x1_trans.vcd");
			$dumpvars(0, mux_2x1_trans_tb);
			$monitor("time = %2d, abit = %1b, bbit = %1b, sbit = %1b result = %1b", $time, abit, bbit, sbit, res);
		end

endmodule

2x1mux_trans/mux_2x1_trans.vcd
$date
	Thu Sep  6 16:05:45 2018
$end
$version
	Icarus Verilog
$end
$timescale
	1s
$end
$scope module mux_2x1_trans_tb $end
$scope module mux_2x1_trans_tb $end
$var wire 1 ! d0 $end
$var wire 1 " d1 $end
$var wire 1 # result $end
$var wire 1 $ s $end
$var wire 1 % s_comp $end
$scope module not_temp $end
$var wire 1 & Gnd $end
$var wire 1 ' Vdd $end
$var wire 1 $ a $end
$var wire 1 % result $end
$upscope $end
$scope module transmission_temp1 $end
$var wire 1 ! a $end
$var wire 1 % en $end
$var wire 1 ( en_comp $end
$var wire 1 # result $end
$scope module not_temp $end
$var wire 1 ) Gnd $end
$var wire 1 * Vdd $end
$var wire 1 % a $end
$var wire 1 ( result $end
$upscope $end
$upscope $end
$scope module transmission_temp2 $end
$var wire 1 " a $end
$var wire 1 $ en $end
$var wire 1 + en_comp $end
$var wire 1 # result $end
$scope module not_temp $end
$var wire 1 , Gnd $end
$var wire 1 - Vdd $end
$var wire 1 $ a $end
$var wire 1 + result $end
$upscope $end
$upscope $end
$upscope $end
$upscope $end
$enddefinitions $end
#0
$dumpvars
1-
0,
1+
1*
0)
0(
1'
0&
1%
0$
0#
0"
0!
$end
#10
1#
1!
#20
0#
0!
1"
#30
1#
1!
#40
0!
0#
0"
1(
0%
0+
1$
#50
1!
#60
0!
1#
1"
#70
1!
