demux1x8_always/demux1x8_always.v
module demux1x8_always(input in, input [2:0]sel, output reg [7:0]result);

always @ *
	begin
		if(sel == 3'b000) begin
			result <= 'h1;
		end
		else if(sel == 3'b001) begin
			result <= 'h2;
		end
		else if(sel == 3'b010) begin
			result <= 'h4;
		end
		else if(sel == 3'b011) begin
			result <= 'h8;
		end
		else if(sel == 3'b100) begin
			result <= 'h10;
		end
		else if(sel == 3'b101) begin
			result <= 'h20;
		end
		else if(sel == 3'b110) begin
			result <= 'h40;
		end
		else result <= 'h80;
	end

endmodule

demux1x8_always/demux1x8_always_tb.v
module demux1x8_always_tb();
reg in;
reg [2:0]sel;
wire [7:0]res;

demux1x8_always demux1x8_always_tb(
	.in(in),
	.sel(sel),
	.result(res)
);

	initial
		begin
				 in=1;
				 sel=3'b000;
			#10; sel=3'b001;
			#10; sel=3'b010;
			#10; sel=3'b011;
			#10; sel=3'b100;
			#10; sel=3'b101;
			#10; sel=3'b110;
			#10; sel=3'b111;
		end

	initial
		begin
			$dumpfile("demux1x8_always.vcd");
			$dumpvars(0, demux1x8_always_tb);
			$monitor("time = %2d, input = %1b, select = %3b result = %h", $time, in, sel, res);
		end

endmodule

demux1x8_always/demux1x8_always.vcd
$date
	Thu Sep 20 15:57:45 2018
$end
$version
	Icarus Verilog
$end
$timescale
	1s
$end
$scope module demux1x8_always_tb $end
$scope module demux1x8_always_tb $end
$var wire 1 ! in $end
$var wire 3 " sel [2:0] $end
$var reg 8 # result [7:0] $end
$upscope $end
$upscope $end
$enddefinitions $end
#0
$dumpvars
b1 #
b0 "
1!
$end
#10
b10 #
b1 "
#20
b100 #
b10 "
#30
b1000 #
b11 "
#40
b10000 #
b100 "
#50
b100000 #
b101 "
#60
b1000000 #
b110 "
#70
b10000000 #
b111 "
