not/not.v
module not_gate(input a, output result);

	supply1 Vdd;
	supply0 Gnd;

	pmos(result, Vdd, a);
	nmos(result, Gnd, a);

endmodule

2x1mux/2x1mux.v
`include "../not/not.v"

module mux_2x1(input d0, input d1, input s, output result);

	wire left_top_d0;
	wire right_top_d1;
	wire left_bottom_d0;
	wire right_bottom_d1;
	wire s_comp;
	wire result_comp;

	not_gate not_temp1(
		.a(s),
		.result(s_comp)
	);

	supply0 Gnd;
	supply1 Vdd;

	nmos(left_bottom_d0, Gnd, d0);
	nmos(right_bottom_d1, Gnd, d1);
	nmos(result_comp, left_bottom_d0, s_comp);
	nmos(result_comp, right_bottom_d1, s);

	pmos(right_top_d1, Vdd, d0);
	pmos(right_top_d1, Vdd, s_comp);
	pmos(result_comp, right_top_d1, s);
	pmos(result_comp, right_top_d1, d1);

	not_gate not_temp2(
		.a(result_comp),
		.result(result)
	);

endmodule

4x1mux/4x1mux.v
`include "../2x1mux/2x1mux.v"

module mux_4x1(input d0, input d1, input d2, input d3, input s0, input s1, output result);

	wire mux1;
	wire mux2;
	wire result_temp;

	mux_2x1 mux_temp1(
		.d0(d0),
		.d1(d1),
		.s(s0),
		.result(mux1)
	);

	mux_2x1 mux_temp2(
		.d0(d2),
		.d1(d3),
		.s(s0),
		.result(mux2)
	);

	mux_2x1 mux_temp3(
		.d0(mux1),
		.d1(mux2),
		.s(s1),
		.result(result_temp)
	);

	not_gate not_temp(
		.a(result_temp),
		.result(result)
	);

endmodule

4x1mux/4x1mux_tb.v
module mux_4x1_tb();
reg a;
reg b;
reg c;
reg d;
reg s1;
reg s2;
wire res;

mux_4x1 mux_4x1_tb(
	.d0(a),
	.d1(b),
	.d2(c),
	.d3(d),
	.s0(s1),
	.s1(s2),
	.result(res)
);

	initial
		begin
				s2 = 0; s1 = 0; d = 0; c = 0; b = 0; a = 0; 
			#10 s2 = 0; s1 = 0; d = 0; c = 0; b = 0; a = 1; 
			#10 s2 = 0; s1 = 0; d = 0; c = 0; b = 1; a = 0; 
			#10 s2 = 0; s1 = 0; d = 0; c = 0; b = 1; a = 1; 
			#10 s2 = 0; s1 = 0; d = 0; c = 1; b = 0; a = 0; 
			#10 s2 = 0; s1 = 0; d = 0; c = 1; b = 0; a = 1; 
			#10 s2 = 0; s1 = 0; d = 0; c = 1; b = 1; a = 0; 
			#10 s2 = 0; s1 = 0; d = 0; c = 1; b = 1; a = 1; 
			#10 s2 = 0; s1 = 0; d = 1; c = 0; b = 0; a = 0; 
			#10 s2 = 0; s1 = 0; d = 1; c = 0; b = 0; a = 1; 
			#10 s2 = 0; s1 = 0; d = 1; c = 0; b = 1; a = 0; 
			#10 s2 = 0; s1 = 0; d = 1; c = 0; b = 1; a = 1; 
			#10 s2 = 0; s1 = 0; d = 1; c = 1; b = 0; a = 0; 
			#10 s2 = 0; s1 = 0; d = 1; c = 1; b = 0; a = 1; 
			#10 s2 = 0; s1 = 0; d = 1; c = 1; b = 1; a = 0; 
			#10 s2 = 0; s1 = 0; d = 1; c = 1; b = 1; a = 1; 
			#10 s2 = 0; s1 = 1; d = 0; c = 0; b = 0; a = 0; 
			#10 s2 = 0; s1 = 1; d = 0; c = 0; b = 0; a = 1; 
			#10 s2 = 0; s1 = 1; d = 0; c = 0; b = 1; a = 0; 
			#10 s2 = 0; s1 = 1; d = 0; c = 0; b = 1; a = 1; 
			#10 s2 = 0; s1 = 1; d = 0; c = 1; b = 0; a = 0; 
			#10 s2 = 0; s1 = 1; d = 0; c = 1; b = 0; a = 1; 
			#10 s2 = 0; s1 = 1; d = 0; c = 1; b = 1; a = 0; 
			#10 s2 = 0; s1 = 1; d = 0; c = 1; b = 1; a = 1; 
			#10 s2 = 0; s1 = 1; d = 1; c = 0; b = 0; a = 0; 
			#10 s2 = 0; s1 = 1; d = 1; c = 0; b = 0; a = 1; 
			#10 s2 = 0; s1 = 1; d = 1; c = 0; b = 1; a = 0; 
			#10 s2 = 0; s1 = 1; d = 1; c = 0; b = 1; a = 1; 
			#10 s2 = 0; s1 = 1; d = 1; c = 1; b = 0; a = 0; 
			#10 s2 = 0; s1 = 1; d = 1; c = 1; b = 0; a = 1; 
			#10 s2 = 0; s1 = 1; d = 1; c = 1; b = 1; a = 0; 
			#10 s2 = 0; s1 = 1; d = 1; c = 1; b = 1; a = 1; 
			#10 s2 = 1; s1 = 0; d = 0; c = 0; b = 0; a = 0; 
			#10 s2 = 1; s1 = 0; d = 0; c = 0; b = 0; a = 1; 
			#10 s2 = 1; s1 = 0; d = 0; c = 0; b = 1; a = 0; 
			#10 s2 = 1; s1 = 0; d = 0; c = 0; b = 1; a = 1; 
			#10 s2 = 1; s1 = 0; d = 0; c = 1; b = 0; a = 0; 
			#10 s2 = 1; s1 = 0; d = 0; c = 1; b = 0; a = 1; 
			#10 s2 = 1; s1 = 0; d = 0; c = 1; b = 1; a = 0; 
			#10 s2 = 1; s1 = 0; d = 0; c = 1; b = 1; a = 1; 
			#10 s2 = 1; s1 = 0; d = 1; c = 0; b = 0; a = 0; 
			#10 s2 = 1; s1 = 0; d = 1; c = 0; b = 0; a = 1; 
			#10 s2 = 1; s1 = 0; d = 1; c = 0; b = 1; a = 0; 
			#10 s2 = 1; s1 = 0; d = 1; c = 0; b = 1; a = 1; 
			#10 s2 = 1; s1 = 0; d = 1; c = 1; b = 0; a = 0; 
			#10 s2 = 1; s1 = 0; d = 1; c = 1; b = 0; a = 1; 
			#10 s2 = 1; s1 = 0; d = 1; c = 1; b = 1; a = 0; 
			#10 s2 = 1; s1 = 0; d = 1; c = 1; b = 1; a = 1; 
			#10 s2 = 1; s1 = 1; d = 0; c = 0; b = 0; a = 0; 
			#10 s2 = 1; s1 = 1; d = 0; c = 0; b = 0; a = 1; 
			#10 s2 = 1; s1 = 1; d = 0; c = 0; b = 1; a = 0; 
			#10 s2 = 1; s1 = 1; d = 0; c = 0; b = 1; a = 1; 
			#10 s2 = 1; s1 = 1; d = 0; c = 1; b = 0; a = 0; 
			#10 s2 = 1; s1 = 1; d = 0; c = 1; b = 0; a = 1; 
			#10 s2 = 1; s1 = 1; d = 0; c = 1; b = 1; a = 0; 
			#10 s2 = 1; s1 = 1; d = 0; c = 1; b = 1; a = 1; 
			#10 s2 = 1; s1 = 1; d = 1; c = 0; b = 0; a = 0; 
			#10 s2 = 1; s1 = 1; d = 1; c = 0; b = 0; a = 1; 
			#10 s2 = 1; s1 = 1; d = 1; c = 0; b = 1; a = 0; 
			#10 s2 = 1; s1 = 1; d = 1; c = 0; b = 1; a = 1; 
			#10 s2 = 1; s1 = 1; d = 1; c = 1; b = 0; a = 0; 
			#10 s2 = 1; s1 = 1; d = 1; c = 1; b = 0; a = 1; 
			#10 s2 = 1; s1 = 1; d = 1; c = 1; b = 1; a = 0; 
			#10 s2 = 1; s1 = 1; d = 1; c = 1; b = 1; a = 1; 
		end

	initial
		begin
			$dumpfile("mux_4x1.vcd");
			$dumpvars(0, mux_4x1_tb);
			$monitor("time = %2d, abit = %1b, bbit = %1b, cbit = %1b, dbit = %1b, s1bit = %1b, s2bit = %1b, result = %1b", $time, a, b, c, d, s1, s2, res);
		end

endmodule

4x1mux/mux_4x1.vcd
$date
	Thu Sep  6 16:04:15 2018
$end
$version
	Icarus Verilog
$end
$timescale
	1s
$end
$scope module mux_4x1_tb $end
$scope module mux_4x1_tb $end
$var wire 1 ! d0 $end
$var wire 1 " d1 $end
$var wire 1 # d2 $end
$var wire 1 $ d3 $end
$var wire 1 % mux1 $end
$var wire 1 & mux2 $end
$var wire 1 ' result $end
$var wire 1 ( result_temp $end
$var wire 1 ) s0 $end
$var wire 1 * s1 $end
$scope module mux_temp1 $end
$var wire 1 + Gnd $end
$var wire 1 , Vdd $end
$var wire 1 ! d0 $end
$var wire 1 " d1 $end
$var wire 1 - left_bottom_d0 $end
$var wire 1 % result $end
$var wire 1 . result_comp $end
$var wire 1 / right_bottom_d1 $end
$var wire 1 0 right_top_d1 $end
$var wire 1 ) s $end
$var wire 1 1 s_comp $end
$scope module not_temp1 $end
$var wire 1 2 Gnd $end
$var wire 1 3 Vdd $end
$var wire 1 ) a $end
$var wire 1 1 result $end
$upscope $end
$scope module not_temp2 $end
$var wire 1 4 Gnd $end
$var wire 1 5 Vdd $end
$var wire 1 . a $end
$var wire 1 % result $end
$upscope $end
$upscope $end
$scope module mux_temp2 $end
$var wire 1 6 Gnd $end
$var wire 1 7 Vdd $end
$var wire 1 # d0 $end
$var wire 1 $ d1 $end
$var wire 1 8 left_bottom_d0 $end
$var wire 1 & result $end
$var wire 1 9 result_comp $end
$var wire 1 : right_bottom_d1 $end
$var wire 1 ; right_top_d1 $end
$var wire 1 ) s $end
$var wire 1 < s_comp $end
$scope module not_temp1 $end
$var wire 1 = Gnd $end
$var wire 1 > Vdd $end
$var wire 1 ) a $end
$var wire 1 < result $end
$upscope $end
$scope module not_temp2 $end
$var wire 1 ? Gnd $end
$var wire 1 @ Vdd $end
$var wire 1 9 a $end
$var wire 1 & result $end
$upscope $end
$upscope $end
$scope module mux_temp3 $end
$var wire 1 A Gnd $end
$var wire 1 B Vdd $end
$var wire 1 % d0 $end
$var wire 1 & d1 $end
$var wire 1 C left_bottom_d0 $end
$var wire 1 ( result $end
$var wire 1 D result_comp $end
$var wire 1 E right_bottom_d1 $end
$var wire 1 F right_top_d1 $end
$var wire 1 * s $end
$var wire 1 G s_comp $end
$scope module not_temp1 $end
$var wire 1 H Gnd $end
$var wire 1 I Vdd $end
$var wire 1 * a $end
$var wire 1 G result $end
$upscope $end
$scope module not_temp2 $end
$var wire 1 J Gnd $end
$var wire 1 K Vdd $end
$var wire 1 D a $end
$var wire 1 ( result $end
$upscope $end
$upscope $end
$scope module not_temp $end
$var wire 1 L Gnd $end
$var wire 1 M Vdd $end
$var wire 1 ( a $end
$var wire 1 ' result $end
$upscope $end
$upscope $end
$upscope $end
$enddefinitions $end
#0
$dumpvars
1M
0L
1K
0J
1I
0H
1G
1F
zE
1D
zC
1B
0A
1@
0?
1>
0=
1<
1;
z:
19
z8
17
06
15
04
13
02
11
10
z/
1.
z-
1,
0+
0*
0)
0(
1'
0&
0%
0$
0#
0"
0!
$end
#10
0-
0C
0'
1(
0D
zF
1%
0.
z0
1!
#20
z-
zC
1'
0(
1D
1F
0%
1.
10
0!
0/
1"
#30
0-
0C
0'
1(
0D
zF
1%
0.
z0
1!
#40
z-
zC
1'
0(
1D
1F
0%
1.
10
0!
z/
0"
08
0E
1&
09
z;
1#
#50
0-
0C
0'
1(
0D
zF
1%
0.
z0
1!
#60
z-
zC
1'
0(
1D
1F
0%
1.
10
0!
0/
1"
#70
0-
0C
0'
1(
0D
zF
1%
0.
z0
1!
#80
z-
zC
1'
0(
1D
1F
0%
1.
10
0!
z/
0"
z8
zE
0&
19
1;
0#
0:
1$
#90
0-
0C
0'
1(
0D
zF
1%
0.
z0
1!
#100
z-
zC
1'
0(
1D
1F
0%
1.
10
0!
0/
1"
#110
0-
0C
0'
1(
0D
zF
1%
0.
z0
1!
#120
z-
zC
1'
0(
1D
1F
0%
1.
10
0!
z/
0"
08
0E
1&
09
z;
1#
#130
0-
0C
0'
1(
0D
zF
1%
0.
z0
1!
#140
z-
zC
1'
0(
1D
1F
0%
1.
10
0!
0/
1"
#150
0-
0C
0'
1(
0D
zF
1%
0.
z0
1!
#160
z-
0!
z/
0"
z8
0#
z:
0$
zC
1'
0(
1D
1F
0%
1.
10
01
zE
0&
19
1;
0<
1)
#170
0-
1!
#180
z-
0!
0/
0C
0'
1(
0D
zF
1%
0.
1"
#190
0-
1!
#200
z-
0!
z/
zC
1'
0(
1D
1F
0%
1.
0"
08
1#
#210
0-
1!
#220
z-
0!
0/
0C
0'
1(
0D
zF
1%
0.
1"
#230
0-
1!
#240
z-
0!
z/
zC
1'
0(
1D
1F
0%
1.
0"
z8
0#
0:
0E
1&
09
1$
#250
0-
1!
#260
z-
0!
0/
0C
0'
1(
0D
zF
1%
0.
1"
#270
0-
1!
#280
z-
0!
z/
zC
1'
0(
1D
1F
0%
1.
0"
08
1#
#290
0-
1!
#300
z-
0!
0/
0C
0'
1(
0D
zF
1%
0.
1"
#310
0-
1!
#320
z-
zC
0%
1.
0!
z/
0"
z8
zE
0&
19
0#
z:
0$
10
11
1;
1<
0)
1'
0(
1D
1F
0G
1*
#330
0-
0C
1%
0.
z0
1!
#340
z-
zC
0%
1.
10
0!
0/
1"
#350
0-
0C
1%
0.
z0
1!
#360
z-
zC
0%
1.
10
0!
z/
0"
08
0E
0'
1(
0D
1&
09
z;
1#
#370
0-
0C
1%
0.
z0
1!
#380
z-
zC
0%
1.
10
0!
0/
1"
#390
0-
0C
1%
0.
z0
1!
#400
z-
zC
0%
1.
10
0!
z/
0"
z8
zE
1'
0(
1D
0&
19
1;
0#
0:
1$
#410
0-
0C
1%
0.
z0
1!
#420
z-
zC
0%
1.
10
0!
0/
1"
#430
0-
0C
1%
0.
z0
1!
#440
z-
zC
0%
1.
10
0!
z/
0"
08
0E
0'
1(
0D
1&
09
z;
1#
#450
0-
0C
1%
0.
z0
1!
#460
z-
zC
0%
1.
10
0!
0/
1"
#470
0-
0C
1%
0.
z0
1!
#480
z-
0!
z/
0"
z8
0#
z:
0$
zC
0%
1.
10
01
zE
1'
0(
1D
0&
19
1;
0<
1)
#490
0-
1!
#500
z-
0!
0/
0C
1%
0.
1"
#510
0-
1!
#520
z-
0!
z/
zC
0%
1.
0"
08
1#
#530
0-
1!
#540
z-
0!
0/
0C
1%
0.
1"
#550
0-
1!
#560
z-
0!
z/
zC
0%
1.
0"
z8
0#
0:
0E
0'
1(
0D
1&
09
1$
#570
0-
1!
#580
z-
0!
0/
0C
1%
0.
1"
#590
0-
1!
#600
z-
0!
z/
zC
0%
1.
0"
08
1#
#610
0-
1!
#620
z-
0!
0/
0C
1%
0.
1"
#630
0-
1!
