mux8x1_always/mux8x1_always.v
module mux8x1_always(input [7:0]in, input [2:0]sel, output reg result);

always @ *
	begin
		if(sel == 3'b000) begin
			result <= in[0];
		end
		else if(sel == 3'b001) begin
			result <= in[1];
		end
		else if(sel == 3'b010) begin
			result <= in[2];
		end
		else if(sel == 3'b011) begin
			result <= in[3];
		end
		else if(sel == 3'b100) begin
			result <= in[4];
		end
		else if(sel == 3'b101) begin
			result <= in[5];
		end
		else if(sel == 3'b110) begin
			result <= in[6];
		end
		else result <= in[7];
	end

endmodule

mux8x1_always/mux8x1_always_tb.v
module mux8x1_always_tb();
reg [7:0]in;
reg [2:0]sel;
wire res;

mux8x1_always mux8x1_always_tb(
	.in(in),
	.sel(sel),
	.result(res)
);

	initial
		begin
				 in=8'b10101010;
				 sel=3'b000;
			#10; sel=3'b001;
			#10; sel=3'b010;
			#10; sel=3'b011;
			#10; sel=3'b100;
			#10; sel=3'b101;
			#10; sel=3'b110;
			#10; sel=3'b111;
		end

	initial
		begin
			$dumpfile("mux8x1_always.vcd");
			$dumpvars(0, mux8x1_always_tb);
			$monitor("time = %2d, input = %8b, select = %3b result = %1b", $time, in, sel, res);
		end

endmodule

mux8x1_always/mux8x1_always.vcd
$date
	Thu Sep 20 15:33:50 2018
$end
$version
	Icarus Verilog
$end
$timescale
	1s
$end
$scope module mux8x1_always_tb $end
$scope module mux8x1_always_tb $end
$var wire 8 ! in [7:0] $end
$var wire 3 " sel [2:0] $end
$var reg 1 # result $end
$upscope $end
$upscope $end
$enddefinitions $end
#0
$dumpvars
0#
b0 "
b10101010 !
$end
#10
1#
b1 "
#20
0#
b10 "
#30
1#
b11 "
#40
0#
b100 "
#50
1#
b101 "
#60
0#
b110 "
#70
1#
b111 "
