not/not.v
module not_gate(input a, output result);

	supply1 Vdd;
	supply0 Gnd;

	pmos(result, Vdd, a);
	nmos(result, Gnd, a);

endmodule

2x1mux/2x1mux.v
`include "../not/not.v"

module mux_2x1(input d0, input d1, input s, output result);

	wire left_top_d0;
	wire right_top_d1;
	wire left_bottom_d0;
	wire right_bottom_d1;
	wire s_comp;
	wire result_comp;

	not_gate not_temp1(
		.a(s),
		.result(s_comp)
	);

	supply0 Gnd;
	supply1 Vdd;

	nmos(left_bottom_d0, Gnd, d0);
	nmos(right_bottom_d1, Gnd, d1);
	nmos(result_comp, left_bottom_d0, s_comp);
	nmos(result_comp, right_bottom_d1, s);

	pmos(right_top_d1, Vdd, d0);
	pmos(right_top_d1, Vdd, s_comp);
	pmos(result_comp, right_top_d1, s);
	pmos(result_comp, right_top_d1, d1);

	not_gate not_temp2(
		.a(result_comp),
		.result(result)
	);

endmodule

2x1mux/2x1mux_tb.v
module mux_2x1_tb();
reg abit;
reg bbit;
reg sbit;
wire res;

mux_2x1 mux_2x1_tb(
	.d0(abit),
	.d1(bbit),
	.s(sbit),
	.result(res)
);

	initial
		begin
				 sbit=0; bbit=0; abit=0;
			#10; sbit=0; bbit=0; abit=1;
			#10; sbit=0; bbit=1; abit=0;
			#10; sbit=0; bbit=1; abit=1;
			#10; sbit=1; bbit=0; abit=0;
			#10; sbit=1; bbit=0; abit=1;
			#10; sbit=1; bbit=1; abit=0;
			#10; sbit=1; bbit=1; abit=1;
		end

	initial
		begin
			$dumpfile("mux_2x1.vcd");
			$dumpvars(0, mux_2x1_tb);
			$monitor("time = %2d, abit = %1b, bbit = %1b, sbit = %1b result = %1b", $time, abit, bbit, sbit, res);
		end

endmodule

2x1mux/mux_2x1.vcd
$date
	Thu Sep  6 15:17:44 2018
$end
$version
	Icarus Verilog
$end
$timescale
	1s
$end
$scope module mux_2x1_tb $end
$scope module mux_2x1_tb $end
$var wire 1 ! Gnd $end
$var wire 1 " Vdd $end
$var wire 1 # d0 $end
$var wire 1 $ d1 $end
$var wire 1 % left_bottom_d0 $end
$var wire 1 & result $end
$var wire 1 ' result_comp $end
$var wire 1 ( right_bottom_d1 $end
$var wire 1 ) right_top_d1 $end
$var wire 1 * s $end
$var wire 1 + s_comp $end
$scope module not_temp1 $end
$var wire 1 , Gnd $end
$var wire 1 - Vdd $end
$var wire 1 * a $end
$var wire 1 + result $end
$upscope $end
$scope module not_temp2 $end
$var wire 1 . Gnd $end
$var wire 1 / Vdd $end
$var wire 1 ' a $end
$var wire 1 & result $end
$upscope $end
$upscope $end
$upscope $end
$enddefinitions $end
#0
$dumpvars
1/
0.
1-
0,
1+
0*
1)
z(
1'
0&
z%
0$
0#
1"
0!
$end
#10
0%
1&
0'
z)
1#
#20
z%
0&
1'
1)
0#
0(
1$
#30
0%
1&
0'
z)
1#
#40
z%
0#
z(
0$
0&
1'
1)
0+
1*
#50
0%
1#
#60
z%
0#
0(
1&
0'
1$
#70
0%
1#
