lab6/e8bitdivide.v
module e8bitdivide(input clock,reset,enable, output reg[7:0] count_out);

wire clock, reset, enable;

always @(posedge clock) begin
	if(reset==1'b1) begin
	count_out<= #1 8'b11111111;
	end
	else if(enable==1'b1) begin
	count_out<=#1 count_out/2'b10;
	end
	end
endmodule

lab6/e8bitdividetb.v
module e8bitdividetb;

reg clock,reset,enable;
wire[7:0] count_out;

e8bitdivide eb(.clock(clock), .reset(reset), .enable(enable), .count_out(count_out));

initial begin
clock=1;
reset=0;
enable=0;
#5 reset=1;
#10 reset=0;
#10 enable=1;
#100 enable=0;
#5 $finish;
end
always begin
#5 clock=~clock;
end

initial begin
$dumpfile("e8bitdivide.vcd");
$dumpvars(0,e8bitdividetb);
$monitor("time = %g, clock =%b, reset=%b, enable=%b, count_out=%b", $time,clock,reset,enable,count_out);
end

endmodule

lab6/e8bitdivide.vcd
$date
	Thu Oct 11 15:45:19 2018
$end
$version
	Icarus Verilog
$end
$timescale
	1s
$end
$scope module e8bitdividetb $end
$var wire 8 ! count_out [7:0] $end
$var reg 1 " clock $end
$var reg 1 # enable $end
$var reg 1 $ reset $end
$scope module eb $end
$var wire 1 " clock $end
$var wire 1 # enable $end
$var wire 1 $ reset $end
$var reg 8 % count_out [7:0] $end
$upscope $end
$upscope $end
$enddefinitions $end
#0
$dumpvars
bx %
0$
0#
1"
bx !
$end
#5
0"
1$
#10
1"
#11
b11111111 !
b11111111 %
#15
0"
0$
#20
1"
#25
0"
1#
#30
1"
#31
b1111111 !
b1111111 %
#35
0"
#40
1"
#41
b111111 !
b111111 %
#45
0"
#50
1"
#51
b11111 !
b11111 %
#55
0"
#60
1"
#61
b1111 !
b1111 %
#65
0"
#70
1"
#71
b111 !
b111 %
#75
0"
#80
1"
#81
b11 !
b11 %
#85
0"
#90
1"
#91
b1 !
b1 %
#95
0"
#100
1"
#101
b0 !
b0 %
#105
0"
#110
1"
#115
0"
#120
1"
#125
0"
0#
