lab6/e8bitcounter.v
module e8bitcounter(input clock,reset,enable, output reg[7:0] count_out);

wire clock, reset, enable;

always @(posedge clock) begin
	if(reset==1'b1) begin
	count_out<= #1 8'b00000000;
	end
	else if(enable==1'b1) begin
	count_out<=#1 count_out+1'b1;
	end
	end
endmodule

lab6/e8bitcountertb.v
module e8bitcountertb;

reg clock,reset,enable;
wire[7:0] count_out;

e8bitcounter eb(.clock(clock), .reset(reset), .enable(enable), .count_out(count_out));

initial begin
clock=1;
reset=0;
enable=0;
#5 reset=1;
#10 reset=0;
#10 enable=1;
#100 enable=0;
#5 $finish;
end
always begin
#5 clock=~clock;
end

initial begin
$dumpfile("e8bitcounter.vcd");
$dumpvars(0,e8bitcountertb);
$monitor("time = %g, clock =%b, reset=%b, enable=%b, count_out=%b", $time,clock,reset,enable,count_out);
end

endmodule

lab6/e8bitcounter.vcd
$date
	Thu Oct 25 16:35:00 2018
$end
$version
	Icarus Verilog
$end
$timescale
	1s
$end
$scope module e8bitcountertb $end
$var wire 8 ! count_out [7:0] $end
$var reg 1 " clock $end
$var reg 1 # enable $end
$var reg 1 $ reset $end
$scope module eb $end
$var wire 1 " clock $end
$var wire 1 # enable $end
$var wire 1 $ reset $end
$var reg 8 % count_out [7:0] $end
$upscope $end
$upscope $end
$enddefinitions $end
#0
$dumpvars
bx %
0$
0#
1"
bx !
$end
#5
0"
1$
#10
1"
#11
b0 !
b0 %
#15
0"
0$
#20
1"
#25
0"
1#
#30
1"
#31
b1 !
b1 %
#35
0"
#40
1"
#41
b10 !
b10 %
#45
0"
#50
1"
#51
b11 !
b11 %
#55
0"
#60
1"
#61
b100 !
b100 %
#65
0"
#70
1"
#71
b101 !
b101 %
#75
0"
#80
1"
#81
b110 !
b110 %
#85
0"
#90
1"
#91
b111 !
b111 %
#95
0"
#100
1"
#101
b1000 !
b1000 %
#105
0"
#110
1"
#111
b1001 !
b1001 %
#115
0"
#120
1"
#121
b1010 !
b1010 %
#125
0"
0#
