lab6/JKflipflop.v
module JKflipflop(q,q1,j,k,c);
output q,q1;
input j,k,c;
reg q,q1;
initial begin q=1'b0; q1=1'b1; end
always @ (posedge c)
  begin
	case({j,k})
		 {1'b0,1'b0}:begin q=q; q1=q1; end
		 {1'b0,1'b1}: begin q=1'b0; q1=1'b1; end
		 {1'b1,1'b0}:begin q=1'b1; q1=1'b0; end
		 {1'b1,1'b1}: begin q=~q; q1=~q1; end
	endcase
   end
endmodule

lab6/JKflipfloptb.v
module JKflipfloptb;

wire q,q1;
reg j,k,c;

JKflipflop t(.q(q), .q1(q1), .j(j), .k(k), .c(c));

initial begin
c=1;
#0  j=0;
       k=1;
#10 j=0;
       k=0;
#10 j=1;
       k=0;
#10 j=0;
       k=0;
#10 j=1;
       k=1;
#60 $finish;
end
always begin
#10 c=~c;
end

initial begin
$dumpfile("JKflipflop.vcd");
$dumpvars(0,JKflipfloptb);
$monitor("time = %2d,  q=%b, q1=%b, j=%b, k=%b, c=%b", $time,q,q1,j,k,c);
end

endmodule

lab6/JKflipflop.vcd
$date
	Thu Oct 25 16:35:24 2018
$end
$version
	Icarus Verilog
$end
$timescale
	1s
$end
$scope module JKflipfloptb $end
$var wire 1 ! q1 $end
$var wire 1 " q $end
$var reg 1 # c $end
$var reg 1 $ j $end
$var reg 1 % k $end
$scope module t $end
$var wire 1 # c $end
$var wire 1 $ j $end
$var wire 1 % k $end
$var reg 1 " q $end
$var reg 1 ! q1 $end
$upscope $end
$upscope $end
$enddefinitions $end
#0
$dumpvars
1%
0$
1#
0"
1!
$end
#10
0%
0#
#20
0!
1"
1$
1#
#30
0$
0#
#40
1!
0"
1%
1$
1#
#50
0#
#60
0!
1"
1#
#70
0#
#80
1!
0"
1#
#90
0#
#100
0!
1"
1#
