lab6/JKmasterSlave.v
module JKmasterSlave(j,k,c,q,qb);
input j,k,c;
output q,qb;
wire o;
and #1 (m,j,qb);
and #1 (n,!k,q);
or (o,m,n);
assign q = o;
assign qb = !q;
endmodule

lab6/JKmasterSlavetb.v
module JKmasterSlavetb;

 reg J;
 reg K;
 reg clk;
 wire Q;
 wire Qbar;

 initial begin
  J = 0;
  K = 0;
  fork
  #4 K = 1;
  #12 J = 1;
  #12 K = 0;
  #20 J = 1;
  #20 K = 1;
  #46 J = 0;
  #46 K = 0;
  #54 K = 1;
  #62 J = 1;
  #62 K = 0;
  #70 K = 1;
  clk = 0;
  join
  #100; $finish;
        end

JKmasterSlave master(J,K,clk,Q,Qbar);

always #4 clk=!clk;

initial begin
$dumpfile("JKmasterSlave.vcd");
$dumpvars(0,JKmasterSlavetb);
$monitor("time = %2d,  q=%b, q1=%b, j=%b, k=%b, c=%b", $time,Q,Qbar,J,K,clk);
end
     
endmodule

lab6/JKmasterSlave.vcd
$date
	Thu Oct 25 16:35:42 2018
$end
$version
	Icarus Verilog
$end
$timescale
	1s
$end
$scope module JKmasterSlavetb $end
$var wire 1 ! Qbar $end
$var wire 1 " Q $end
$var reg 1 # J $end
$var reg 1 $ K $end
$var reg 1 % clk $end
$scope module master $end
$var wire 1 % c $end
$var wire 1 # j $end
$var wire 1 $ k $end
$var wire 1 & m $end
$var wire 1 ' n $end
$var wire 1 ( o $end
$var wire 1 " q $end
$var wire 1 ! qb $end
$upscope $end
$upscope $end
$enddefinitions $end
#0
$dumpvars
x(
x'
x&
0%
0$
0#
x"
x!
$end
#1
0&
#4
1%
1$
#5
1!
0"
0(
0'
#8
0%
#12
1%
1#
0$
#13
0!
1"
1(
1&
#14
0&
1'
#16
0%
#20
1%
1$
#21
1!
0"
0(
0'
#22
0!
1"
1(
1&
#23
1!
0"
0(
0&
#24
0!
1"
1(
1&
0%
#25
1!
0"
0(
0&
#26
0!
1"
1(
1&
#27
1!
0"
0(
0&
#28
0!
1"
1(
1&
1%
#29
1!
0"
0(
0&
#30
0!
1"
1(
1&
#31
1!
0"
0(
0&
#32
0!
1"
1(
1&
0%
#33
1!
0"
0(
0&
#34
0!
1"
1(
1&
#35
1!
0"
0(
0&
#36
0!
1"
1(
1&
1%
#37
1!
0"
0(
0&
#38
0!
1"
1(
1&
#39
1!
0"
0(
0&
#40
0!
1"
1(
1&
0%
#41
1!
0"
0(
0&
#42
0!
1"
1(
1&
#43
1!
0"
0(
0&
#44
0!
1"
1(
1&
1%
#45
1!
0"
0(
0&
#46
0!
1"
1(
1&
0#
0$
#47
1'
0&
#48
0%
#52
1%
#54
1$
#55
1!
0"
0(
0'
#56
0%
#60
1%
#62
1#
0$
#63
0!
1"
1(
1&
#64
0&
1'
0%
#68
1%
#70
1$
#71
1!
0"
0(
0'
#72
0!
1"
1(
1&
0%
#73
1!
0"
0(
0&
#74
0!
1"
1(
1&
#75
1!
0"
0(
0&
#76
0!
1"
1(
1&
1%
#77
1!
0"
0(
0&
#78
0!
1"
1(
1&
#79
1!
0"
0(
0&
#80
0!
1"
1(
1&
0%
#81
1!
0"
0(
0&
#82
0!
1"
1(
1&
#83
1!
0"
0(
0&
#84
0!
1"
1(
1&
1%
#85
1!
0"
0(
0&
#86
0!
1"
1(
1&
#87
1!
0"
0(
0&
#88
0!
1"
1(
1&
0%
#89
1!
0"
0(
0&
#90
0!
1"
1(
1&
#91
1!
0"
0(
0&
#92
0!
1"
1(
1&
1%
#93
1!
0"
0(
0&
#94
0!
1"
1(
1&
#95
1!
0"
0(
0&
#96
0!
1"
1(
1&
0%
#97
1!
0"
0(
0&
#98
0!
1"
1(
1&
#99
1!
0"
0(
0&
#100
0!
1"
1(
1&
1%
#101
1!
0"
0(
0&
#102
0!
1"
1(
1&
#103
1!
0"
0(
0&
#104
0!
1"
1(
1&
0%
#105
1!
0"
0(
0&
#106
0!
1"
1(
1&
#107
1!
0"
0(
0&
#108
0!
1"
1(
1&
1%
#109
1!
0"
0(
0&
#110
0!
1"
1(
1&
#111
1!
0"
0(
0&
#112
0!
1"
1(
1&
0%
#113
1!
0"
0(
0&
#114
0!
1"
1(
1&
#115
1!
0"
0(
0&
#116
0!
1"
1(
1&
1%
#117
1!
0"
0(
0&
#118
0!
1"
1(
1&
#119
1!
0"
0(
0&
#120
0!
1"
1(
1&
0%
#121
1!
0"
0(
0&
#122
0!
1"
1(
1&
#123
1!
0"
0(
0&
#124
0!
1"
1(
1&
1%
#125
1!
0"
0(
0&
#126
0!
1"
1(
1&
#127
1!
0"
0(
0&
#128
0!
1"
1(
1&
0%
#129
1!
0"
0(
0&
#130
0!
1"
1(
1&
#131
1!
0"
0(
0&
#132
0!
1"
1(
1&
1%
#133
1!
0"
0(
0&
#134
0!
1"
1(
1&
#135
1!
0"
0(
0&
#136
0!
1"
1(
1&
0%
#137
1!
0"
0(
0&
#138
0!
1"
1(
1&
#139
1!
0"
0(
0&
#140
0!
1"
1(
1&
1%
#141
1!
0"
0(
0&
#142
0!
1"
1(
1&
#143
1!
0"
0(
0&
#144
0!
1"
1(
1&
0%
#145
1!
0"
0(
0&
#146
0!
1"
1(
1&
#147
1!
0"
0(
0&
#148
0!
1"
1(
1&
1%
#149
1!
0"
0(
0&
#150
0!
1"
1(
1&
#151
1!
0"
0(
0&
#152
0!
1"
1(
1&
0%
#153
1!
0"
0(
0&
#154
0!
1"
1(
1&
#155
1!
0"
0(
0&
#156
0!
1"
1(
1&
1%
#157
1!
0"
0(
0&
#158
0!
1"
1(
1&
#159
1!
0"
0(
0&
#160
0!
1"
1(
1&
0%
#161
1!
0"
0(
0&
#162
0!
1"
1(
1&
#163
1!
0"
0(
0&
#164
0!
1"
1(
1&
1%
#165
1!
0"
0(
0&
#166
0!
1"
1(
1&
#167
1!
0"
0(
0&
#168
0!
1"
1(
1&
0%
#169
1!
0"
0(
0&
#170
0!
1"
1(
1&
#171
1!
0"
0(
0&
#172
0!
1"
1(
1&
1%
#173
1!
0"
0(
0&
#174
0!
1"
1(
1&
#175
1!
0"
0(
0&
#176
0!
1"
1(
1&
0%
#177
1!
0"
0(
0&
#178
0!
1"
1(
1&
#179
1!
0"
0(
0&
#180
0!
1"
1(
1&
1%
#181
1!
0"
0(
0&
#182
0!
1"
1(
1&
#183
1!
0"
0(
0&
#184
0!
1"
1(
1&
0%
#185
1!
0"
0(
0&
#186
0!
1"
1(
1&
#187
1!
0"
0(
0&
#188
0!
1"
1(
1&
1%
#189
1!
0"
0(
0&
#190
0!
1"
1(
1&
#191
1!
0"
0(
0&
#192
0!
1"
1(
1&
0%
#193
1!
0"
0(
0&
#194
0!
1"
1(
1&
#195
1!
0"
0(
0&
#196
0!
1"
1(
1&
1%
#197
1!
0"
0(
0&
#198
0!
1"
1(
1&
#199
1!
0"
0(
0&
#200
0!
1"
1(
1&
0%
#201
1!
0"
0(
0&
#202
0!
1"
1(
1&
#203
1!
0"
0(
0&
#204
0!
1"
1(
1&
1%
#205
1!
0"
0(
0&
#206
0!
1"
1(
1&
#207
1!
0"
0(
0&
#208
0!
1"
1(
1&
0%
#209
1!
0"
0(
0&
#210
0!
1"
1(
1&
#211
1!
0"
0(
0&
#212
0!
1"
1(
1&
1%
#213
1!
0"
0(
0&
#214
0!
1"
1(
1&
#215
1!
0"
0(
0&
#216
0!
1"
1(
1&
0%
#217
1!
0"
0(
0&
#218
0!
1"
1(
1&
#219
1!
0"
0(
0&
#220
0!
1"
1(
1&
1%
#221
1!
0"
0(
0&
#222
0!
1"
1(
1&
#223
1!
0"
0(
0&
#224
0!
1"
1(
1&
0%
#225
1!
0"
0(
0&
#226
0!
1"
1(
1&
#227
1!
0"
0(
0&
#228
0!
1"
1(
1&
1%
#229
1!
0"
0(
0&
#230
0!
1"
1(
1&
#231
1!
0"
0(
0&
#232
0!
1"
1(
1&
0%
#233
1!
0"
0(
0&
#234
0!
1"
1(
1&
#235
1!
0"
0(
0&
#236
0!
1"
1(
1&
1%
#237
1!
0"
0(
0&
#238
0!
1"
1(
1&
#239
1!
0"
0(
0&
#240
0!
1"
1(
1&
0%
#241
1!
0"
0(
0&
#242
0!
1"
1(
1&
#243
1!
0"
0(
0&
#244
0!
1"
1(
1&
1%
#245
1!
0"
0(
0&
#246
0!
1"
1(
1&
#247
1!
0"
0(
0&
#248
0!
1"
1(
1&
0%
#249
1!
0"
0(
0&
#250
0!
1"
1(
1&
#251
1!
0"
0(
0&
#252
0!
1"
1(
1&
1%
#253
1!
0"
0(
0&
#254
0!
1"
1(
1&
#255
1!
0"
0(
0&
#256
0!
1"
1(
1&
0%
#257
1!
0"
0(
0&
#258
0!
1"
1(
1&
#259
1!
0"
0(
0&
#260
0!
1"
1(
1&
1%
#261
1!
0"
0(
0&
#262
0!
1"
1(
1&
#263
1!
0"
0(
0&
#264
0!
1"
1(
1&
0%
#265
1!
0"
0(
0&
#266
0!
1"
1(
1&
#267
1!
0"
0(
0&
#268
0!
1"
1(
1&
1%
#269
1!
0"
0(
0&
#270
0!
1"
1(
1&
#271
1!
0"
0(
0&
#272
0!
1"
1(
1&
0%
#273
1!
0"
0(
0&
#274
0!
1"
1(
1&
#275
1!
0"
0(
0&
#276
0!
1"
1(
1&
1%
#277
1!
0"
0(
0&
#278
0!
1"
1(
1&
#279
1!
0"
0(
0&
#280
0!
1"
1(
1&
0%
#281
1!
0"
0(
0&
#282
0!
1"
1(
1&
#283
1!
0"
0(
0&
#284
0!
1"
1(
1&
1%
#285
1!
0"
0(
0&
#286
0!
1"
1(
1&
#287
1!
0"
0(
0&
#288
0!
1"
1(
1&
0%
#289
1!
0"
0(
0&
#290
0!
1"
1(
1&
#291
1!
0"
0(
0&
#292
0!
1"
1(
1&
1%
#293
1!
0"
0(
0&
#294
0!
1"
1(
1&
#295
1!
0"
0(
0&
#296
0!
1"
1(
1&
0%
#297
1!
0"
0(
0&
#298
0!
1"
1(
1&
#299
1!
0"
0(
0&
#300
0!
1"
1(
1&
1%
#301
1!
0"
0(
0&
#302
0!
1"
1(
1&
#303
1!
0"
0(
0&
#304
0!
1"
1(
1&
0%
#305
1!
0"
0(
0&
#306
0!
1"
1(
1&
#307
1!
0"
0(
0&
#308
0!
1"
1(
1&
1%
#309
1!
0"
0(
0&
#310
0!
1"
1(
1&
#311
1!
0"
0(
0&
#312
0!
1"
1(
1&
0%
#313
1!
0"
0(
0&
#314
0!
1"
1(
1&
#315
1!
0"
0(
0&
#316
0!
1"
1(
1&
1%
#317
1!
0"
0(
0&
#318
0!
1"
1(
1&
#319
1!
0"
0(
0&
#320
0!
1"
1(
1&
0%
#321
1!
0"
0(
0&
#322
0!
1"
1(
1&
#323
1!
0"
0(
0&
#324
0!
1"
1(
1&
1%
#325
1!
0"
0(
0&
#326
0!
1"
1(
1&
#327
1!
0"
0(
0&
#328
0!
1"
1(
1&
0%
#329
1!
0"
0(
0&
#330
0!
1"
1(
1&
#331
1!
0"
0(
0&
#332
0!
1"
1(
1&
1%
#333
1!
0"
0(
0&
#334
0!
1"
1(
1&
#335
1!
0"
0(
0&
#336
0!
1"
1(
1&
0%
#337
1!
0"
0(
0&
#338
0!
1"
1(
1&
#339
1!
0"
0(
0&
#340
0!
1"
1(
1&
1%
#341
1!
0"
0(
0&
#342
0!
1"
1(
1&
#343
1!
0"
0(
0&
#344
0!
1"
1(
1&
0%
#345
1!
0"
0(
0&
#346
0!
1"
1(
1&
#347
1!
0"
0(
0&
#348
0!
1"
1(
1&
1%
#349
1!
0"
0(
0&
#350
0!
1"
1(
1&
#351
1!
0"
0(
0&
#352
0!
1"
1(
1&
0%
#353
1!
0"
0(
0&
#354
0!
1"
1(
1&
#355
1!
0"
0(
0&
#356
0!
1"
1(
1&
1%
#357
1!
0"
0(
0&
#358
0!
1"
1(
1&
#359
1!
0"
0(
0&
#360
0!
1"
1(
1&
0%
#361
1!
0"
0(
0&
#362
0!
1"
1(
1&
#363
1!
0"
0(
0&
#364
0!
1"
1(
1&
1%
#365
1!
0"
0(
0&
#366
0!
1"
1(
1&
#367
1!
0"
0(
0&
#368
0!
1"
1(
1&
0%
#369
1!
0"
0(
0&
#370
0!
1"
1(
1&
#371
1!
0"
0(
0&
#372
0!
1"
1(
1&
1%
#373
1!
0"
0(
0&
#374
0!
1"
1(
1&
#375
1!
0"
0(
0&
#376
0!
1"
1(
1&
0%
#377
1!
0"
0(
0&
#378
0!
1"
1(
1&
#379
1!
0"
0(
0&
#380
0!
1"
1(
1&
1%
#381
1!
0"
0(
0&
#382
0!
1"
1(
1&
#383
1!
0"
0(
0&
#384
0!
1"
1(
1&
0%
#385
1!
0"
0(
0&
#386
0!
1"
1(
1&
#387
1!
0"
0(
0&
#388
0!
1"
1(
1&
1%
#389
1!
0"
0(
0&
#390
0!
1"
1(
1&
#391
1!
0"
0(
0&
#392
0!
1"
1(
1&
0%
#393
1!
0"
0(
0&
#394
0!
1"
1(
1&
#395
1!
0"
0(
0&
#396
0!
1"
1(
1&
1%
#397
1!
0"
0(
0&
#398
0!
1"
1(
1&
#399
1!
0"
0(
0&
#400
0!
1"
1(
1&
0%
#401
1!
0"
0(
0&
#402
0!
1"
1(
1&
#403
1!
0"
0(
0&
#404
0!
1"
1(
1&
1%
#405
1!
0"
0(
0&
#406
0!
1"
1(
1&
#407
1!
0"
0(
0&
#408
0!
1"
1(
1&
0%
#409
1!
0"
0(
0&
#410
0!
1"
1(
1&
#411
1!
0"
0(
0&
#412
0!
1"
1(
1&
1%
#413
1!
0"
0(
0&
#414
0!
1"
1(
1&
#415
1!
0"
0(
0&
#416
0!
1"
1(
1&
0%
#417
1!
0"
0(
0&
#418
0!
1"
1(
1&
#419
1!
0"
0(
0&
#420
0!
1"
1(
1&
1%
#421
1!
0"
0(
0&
#422
0!
1"
1(
1&
#423
1!
0"
0(
0&
#424
0!
1"
1(
1&
0%
#425
1!
0"
0(
0&
#426
0!
1"
1(
1&
#427
1!
0"
0(
0&
#428
0!
1"
1(
1&
1%
#429
1!
0"
0(
0&
#430
0!
1"
1(
1&
#431
1!
0"
0(
0&
#432
0!
1"
1(
1&
0%
#433
1!
0"
0(
0&
#434
0!
1"
1(
1&
#435
1!
0"
0(
0&
#436
0!
1"
1(
1&
1%
#437
1!
0"
0(
0&
#438
0!
1"
1(
1&
#439
1!
0"
0(
0&
#440
0!
1"
1(
1&
0%
#441
1!
0"
0(
0&
#442
0!
1"
1(
1&
#443
1!
0"
0(
0&
#444
0!
1"
1(
1&
1%
#445
1!
0"
0(
0&
#446
0!
1"
1(
1&
#447
1!
0"
0(
0&
#448
0!
1"
1(
1&
0%
#449
1!
0"
0(
0&
#450
0!
1"
1(
1&
#451
1!
0"
0(
0&
#452
0!
1"
1(
1&
1%
#453
1!
0"
0(
0&
#454
0!
1"
1(
1&
#455
1!
0"
0(
0&
#456
0!
1"
1(
1&
0%
#457
1!
0"
0(
0&
#458
0!
1"
1(
1&
#459
1!
0"
0(
0&
#460
0!
1"
1(
1&
1%
#461
1!
0"
0(
0&
#462
0!
1"
1(
1&
#463
1!
0"
0(
0&
#464
0!
1"
1(
1&
0%
#465
1!
0"
0(
0&
#466
0!
1"
1(
1&
#467
1!
0"
0(
0&
#468
0!
1"
1(
1&
1%
#469
1!
0"
0(
0&
#470
0!
1"
1(
1&
#471
1!
0"
0(
0&
#472
0!
1"
1(
1&
0%
#473
1!
0"
0(
0&
#474
0!
1"
1(
1&
#475
1!
0"
0(
0&
#476
0!
1"
1(
1&
1%
#477
1!
0"
0(
0&
#478
0!
1"
1(
1&
#479
1!
0"
0(
0&
#480
0!
1"
1(
1&
0%
#481
1!
0"
0(
0&
#482
0!
1"
1(
1&
#483
1!
0"
0(
0&
#484
0!
1"
1(
1&
1%
#485
1!
0"
0(
0&
#486
0!
1"
1(
1&
#487
1!
0"
0(
0&
#488
0!
1"
1(
1&
0%
#489
1!
0"
0(
0&
#490
0!
1"
1(
1&
#491
1!
0"
0(
0&
#492
0!
1"
1(
1&
1%
#493
1!
0"
0(
0&
#494
0!
1"
1(
1&
#495
1!
0"
0(
0&
#496
0!
1"
1(
1&
0%
#497
1!
0"
0(
0&
#498
0!
1"
1(
1&
#499
1!
0"
0(
0&
#500
0!
1"
1(
1&
1%
#501
1!
0"
0(
0&
#502
0!
1"
1(
1&
#503
1!
0"
0(
0&
#504
0!
1"
1(
1&
0%
#505
1!
0"
0(
0&
#506
0!
1"
1(
1&
#507
1!
0"
0(
0&
#508
0!
1"
1(
1&
1%
#509
1!
0"
0(
0&
#510
0!
1"
1(
1&
#511
1!
0"
0(
0&
#512
0!
1"
1(
1&
0%
#513
1!
0"
0(
0&
#514
0!
1"
1(
1&
#515
1!
0"
0(
0&
#516
0!
1"
1(
1&
1%
#517
1!
0"
0(
0&
#518
0!
1"
1(
1&
#519
1!
0"
0(
0&
#520
0!
1"
1(
1&
0%
#521
1!
0"
0(
0&
#522
0!
1"
1(
1&
#523
1!
0"
0(
0&
#524
0!
1"
1(
1&
1%
#525
1!
0"
0(
0&
#526
0!
1"
1(
1&
#527
1!
0"
0(
0&
#528
0!
1"
1(
1&
0%
#529
1!
0"
0(
0&
#530
0!
1"
1(
1&
#531
1!
0"
0(
0&
#532
0!
1"
1(
1&
1%
#533
1!
0"
0(
0&
#534
0!
1"
1(
1&
#535
1!
0"
0(
0&
#536
0!
1"
1(
1&
0%
#537
1!
0"
0(
0&
#538
0!
1"
1(
1&
#539
1!
0"
0(
0&
#540
0!
1"
1(
1&
1%
#541
1!
0"
0(
0&
#542
0!
1"
1(
1&
#543
1!
0"
0(
0&
#544
0!
1"
1(
1&
0%
#545
1!
0"
0(
0&
#546
0!
1"
1(
1&
#547
1!
0"
0(
0&
#548
0!
1"
1(
1&
1%
#549
1!
0"
0(
0&
#550
0!
1"
1(
1&
#551
1!
0"
0(
0&
#552
0!
1"
1(
1&
0%
#553
1!
0"
0(
0&
#554
0!
1"
1(
1&
#555
1!
0"
0(
0&
#556
0!
1"
1(
1&
1%
#557
1!
0"
0(
0&
#558
0!
1"
1(
1&
#559
1!
0"
0(
0&
#560
0!
1"
1(
1&
0%
#561
1!
0"
0(
0&
#562
0!
1"
1(
1&
#563
1!
0"
0(
0&
#564
0!
1"
1(
1&
1%
#565
1!
0"
0(
0&
#566
0!
1"
1(
1&
#567
1!
0"
0(
0&
#568
0!
1"
1(
1&
0%
#569
1!
0"
0(
0&
#570
0!
1"
1(
1&
#571
1!
0"
0(
0&
#572
0!
1"
1(
1&
1%
#573
1!
0"
0(
0&
#574
0!
1"
1(
1&
#575
1!
0"
0(
0&
#576
0!
1"
1(
1&
0%
#577
1!
0"
0(
0&
#578
0!
1"
1(
1&
#579
1!
0"
0(
0&
#580
0!
1"
1(
1&
1%
#581
1!
0"
0(
0&
#582
0!
1"
1(
1&
#583
1!
0"
0(
0&
#584
0!
1"
1(
1&
0%
#585
1!
0"
0(
0&
#586
0!
1"
1(
1&
#587
1!
0"
0(
0&
#588
0!
1"
1(
1&
1%
#589
1!
0"
0(
0&
#590
0!
1"
1(
1&
#591
1!
0"
0(
0&
#592
0!
1"
1(
1&
0%
#593
1!
0"
0(
0&
#594
0!
1"
1(
1&
#595
1!
0"
0(
0&
#596
0!
1"
1(
1&
1%
#597
1!
0"
0(
0&
#598
0!
1"
1(
1&
#599
1!
0"
0(
0&
#600
0!
1"
1(
1&
0%
#601
1!
0"
0(
0&
#602
0!
1"
1(
1&
#603
1!
0"
0(
0&
#604
0!
1"
1(
1&
1%
#605
1!
0"
0(
0&
#606
0!
1"
1(
1&
#607
1!
0"
0(
0&
#608
0!
1"
1(
1&
0%
#609
1!
0"
0(
0&
#610
0!
1"
1(
1&
#611
1!
0"
0(
0&
#612
0!
1"
1(
1&
1%
#613
1!
0"
0(
0&
#614
0!
1"
1(
1&
#615
1!
0"
0(
0&
#616
0!
1"
1(
1&
0%
#617
1!
0"
0(
0&
#618
0!
1"
1(
1&
#619
1!
0"
0(
0&
#620
0!
1"
1(
1&
1%
#621
1!
0"
0(
0&
#622
0!
1"
1(
1&
#623
1!
0"
0(
0&
#624
0!
1"
1(
1&
0%
#625
1!
0"
0(
0&
#626
0!
1"
1(
1&
#627
1!
0"
0(
0&
#628
0!
1"
1(
1&
1%
#629
1!
0"
0(
0&
#630
0!
1"
1(
1&
#631
1!
0"
0(
0&
#632
0!
1"
1(
1&
0%
#633
1!
0"
0(
0&
#634
0!
1"
1(
1&
#635
1!
0"
0(
0&
#636
0!
1"
1(
1&
1%
#637
1!
0"
0(
0&
#638
0!
1"
1(
1&
#639
1!
0"
0(
0&
#640
0!
1"
1(
1&
0%
#641
1!
0"
0(
0&
#642
0!
1"
1(
1&
#643
1!
0"
0(
0&
#644
0!
1"
1(
1&
1%
#645
1!
0"
0(
0&
#646
0!
1"
1(
1&
#647
1!
0"
0(
0&
#648
0!
1"
1(
1&
0%
#649
1!
0"
0(
0&
#650
0!
1"
1(
1&
#651
1!
0"
0(
0&
#652
0!
1"
1(
1&
1%
#653
1!
0"
0(
0&
#654
0!
1"
1(
1&
#655
1!
0"
0(
0&
#656
0!
1"
1(
1&
0%
#657
1!
0"
0(
0&
#658
0!
1"
1(
1&
#659
1!
0"
0(
0&
#660
0!
1"
1(
1&
1%
#661
1!
0"
0(
0&
#662
0!
1"
1(
1&
#663
1!
0"
0(
0&
#664
0!
1"
1(
1&
0%
#665
1!
0"
0(
0&
#666
0!
1"
1(
1&
#667
1!
0"
0(
0&
#668
0!
1"
1(
1&
1%
#669
1!
0"
0(
0&
#670
0!
1"
1(
1&
#671
1!
0"
0(
0&
#672
0!
1"
1(
1&
0%
#673
1!
0"
0(
0&
#674
0!
1"
1(
1&
#675
1!
0"
0(
0&
#676
0!
1"
1(
1&
1%
#677
1!
0"
0(
0&
#678
0!
1"
1(
1&
#679
1!
0"
0(
0&
#680
0!
1"
1(
1&
0%
#681
1!
0"
0(
0&
#682
0!
1"
1(
1&
#683
1!
0"
0(
0&
#684
0!
1"
1(
1&
1%
#685
1!
0"
0(
0&
#686
0!
1"
1(
1&
#687
1!
0"
0(
0&
#688
0!
1"
1(
1&
0%
#689
1!
0"
0(
0&
#690
0!
1"
1(
1&
#691
1!
0"
0(
0&
#692
0!
1"
1(
1&
1%
#693
1!
0"
0(
0&
#694
0!
1"
1(
1&
#695
1!
0"
0(
0&
#696
0!
1"
1(
1&
0%
#697
1!
0"
0(
0&
#698
0!
1"
1(
1&
#699
1!
0"
0(
0&
#700
0!
1"
1(
1&
1%
#701
1!
0"
0(
0&
#702
0!
1"
1(
1&
#703
1!
0"
0(
0&
#704
0!
1"
1(
1&
0%
#705
1!
0"
0(
0&
#706
0!
1"
1(
1&
#707
1!
0"
0(
0&
#708
0!
1"
1(
1&
1%
#709
1!
0"
0(
0&
#710
0!
1"
1(
1&
#711
1!
0"
0(
0&
#712
0!
1"
1(
1&
0%
#713
1!
0"
0(
0&
#714
0!
1"
1(
1&
#715
1!
0"
0(
0&
#716
0!
1"
1(
1&
1%
#717
1!
0"
0(
0&
#718
0!
1"
1(
1&
#719
1!
0"
0(
0&
#720
0!
1"
1(
1&
0%
#721
1!
0"
0(
0&
#722
0!
1"
1(
1&
#723
1!
0"
0(
0&
#724
0!
1"
1(
1&
1%
#725
1!
0"
0(
0&
#726
0!
1"
1(
1&
#727
1!
0"
0(
0&
#728
0!
1"
1(
1&
0%
#729
1!
0"
0(
0&
#730
0!
1"
1(
1&
#731
1!
0"
0(
0&
#732
0!
1"
1(
1&
1%
#733
1!
0"
0(
0&
#734
0!
1"
1(
1&
#735
1!
0"
0(
0&
#736
0!
1"
1(
1&
0%
#737
1!
0"
0(
0&
#738
0!
1"
1(
1&
#739
1!
0"
0(
0&
#740
0!
1"
1(
1&
1%
#741
1!
0"
0(
0&
#742
0!
1"
1(
1&
#743
1!
0"
0(
0&
#744
0!
1"
1(
1&
0%
#745
1!
0"
0(
0&
#746
0!
1"
1(
1&
#747
1!
0"
0(
0&
#748
0!
1"
1(
1&
1%
#749
1!
0"
0(
0&
#750
0!
1"
1(
1&
#751
1!
0"
0(
0&
#752
0!
1"
1(
1&
0%
#753
1!
0"
0(
0&
#754
0!
1"
1(
1&
#755
1!
0"
0(
0&
#756
0!
1"
1(
1&
1%
#757
1!
0"
0(
0&
#758
0!
1"
1(
1&
#759
1!
0"
0(
0&
#760
0!
1"
1(
1&
0%
#761
1!
0"
0(
0&
#762
0!
1"
1(
1&
#763
1!
0"
0(
0&
#764
0!
1"
1(
1&
1%
#765
1!
0"
0(
0&
#766
0!
1"
1(
1&
#767
1!
0"
0(
0&
#768
0!
1"
1(
1&
0%
#769
1!
0"
0(
0&
#770
0!
1"
1(
1&
#771
1!
0"
0(
0&
#772
0!
1"
1(
1&
1%
#773
1!
0"
0(
0&
#774
0!
1"
1(
1&
#775
1!
0"
0(
0&
#776
0!
1"
1(
1&
0%
#777
1!
0"
0(
0&
#778
0!
1"
1(
1&
#779
1!
0"
0(
0&
#780
0!
1"
1(
1&
1%
#781
1!
0"
0(
0&
#782
0!
1"
1(
1&
#783
1!
0"
0(
0&
#784
0!
1"
1(
1&
0%
#785
1!
0"
0(
0&
#786
0!
1"
1(
1&
#787
1!
0"
0(
0&
#788
0!
1"
1(
1&
1%
#789
1!
0"
0(
0&
#790
0!
1"
1(
1&
#791
1!
0"
0(
0&
#792
0!
1"
1(
1&
0%
#793
1!
0"
0(
0&
#794
0!
1"
1(
1&
#795
1!
0"
0(
0&
#796
0!
1"
1(
1&
1%
#797
1!
0"
0(
0&
#798
0!
1"
1(
1&
#799
1!
0"
0(
0&
#800
0!
1"
1(
1&
0%
#801
1!
0"
0(
0&
#802
0!
1"
1(
1&
#803
1!
0"
0(
0&
#804
0!
1"
1(
1&
1%
#805
1!
0"
0(
0&
#806
0!
1"
1(
1&
#807
1!
0"
0(
0&
#808
0!
1"
1(
1&
0%
#809
1!
0"
0(
0&
#810
0!
1"
1(
1&
#811
1!
0"
0(
0&
#812
0!
1"
1(
1&
1%
#813
1!
0"
0(
0&
#814
0!
1"
1(
1&
#815
1!
0"
0(
0&
#816
0!
1"
1(
1&
0%
#817
1!
0"
0(
0&
#818
0!
1"
1(
1&
#819
1!
0"
0(
0&
#820
0!
1"
1(
1&
1%
#821
1!
0"
0(
0&
#822
0!
1"
1(
1&
#823
1!
0"
0(
0&
#824
0!
1"
1(
1&
0%
#825
1!
0"
0(
0&
#826
0!
1"
1(
1&
#827
1!
0"
0(
0&
#828
0!
1"
1(
1&
1%
#829
1!
0"
0(
0&
#830
0!
1"
1(
1&
#831
1!
0"
0(
0&
#832
0!
1"
1(
1&
0%
#833
1!
0"
0(
0&
#834
0!
1"
1(
1&
#835
1!
0"
0(
0&
#836
0!
1"
1(
1&
1%
#837
1!
0"
0(
0&
#838
0!
1"
1(
1&
#839
1!
0"
0(
0&
#840
0!
1"
1(
1&
0%
#841
1!
0"
0(
0&
#842
0!
1"
1(
1&
#843
1!
0"
0(
0&
#844
0!
1"
1(
1&
1%
#845
1!
0"
0(
0&
#846
0!
1"
1(
1&
#847
1!
0"
0(
0&
#848
0!
1"
1(
1&
0%
#849
1!
0"
0(
0&
#850
0!
1"
1(
1&
#851
1!
0"
0(
0&
#852
0!
1"
1(
1&
1%
#853
1!
0"
0(
0&
#854
0!
1"
1(
1&
#855
1!
0"
0(
0&
#856
0!
1"
1(
1&
0%
#857
1!
0"
0(
0&
#858
0!
1"
1(
1&
#859
1!
0"
0(
0&
#860
0!
1"
1(
1&
1%
#861
1!
0"
0(
0&
#862
0!
1"
1(
1&
#863
1!
0"
0(
0&
#864
0!
1"
1(
1&
0%
#865
1!
0"
0(
0&
#866
0!
1"
1(
1&
#867
1!
0"
0(
0&
#868
0!
1"
1(
1&
1%
#869
1!
0"
0(
0&
#870
0!
1"
1(
1&
#871
1!
0"
0(
0&
#872
0!
1"
1(
1&
0%
#873
1!
0"
0(
0&
#874
0!
1"
1(
1&
#875
1!
0"
0(
0&
#876
0!
1"
1(
1&
1%
#877
1!
0"
0(
0&
#878
0!
1"
1(
1&
#879
1!
0"
0(
0&
#880
0!
1"
1(
1&
0%
#881
1!
0"
0(
0&
#882
0!
1"
1(
1&
#883
1!
0"
0(
0&
#884
0!
1"
1(
1&
1%
#885
1!
0"
0(
0&
#886
0!
1"
1(
1&
#887
1!
0"
0(
0&
#888
0!
1"
1(
1&
0%
#889
1!
0"
0(
0&
#890
0!
1"
1(
1&
#891
1!
0"
0(
0&
#892
0!
1"
1(
1&
1%
#893
1!
0"
0(
0&
#894
0!
1"
1(
1&
#895
1!
0"
0(
0&
#896
0!
1"
1(
1&
0%
#897
1!
0"
0(
0&
#898
0!
1"
1(
1&
#899
1!
0"
0(
0&
#900
0!
1"
1(
1&
1%
#901
1!
0"
0(
0&
#902
0!
1"
1(
1&
#903
1!
0"
0(
0&
#904
0!
1"
1(
1&
0%
#905
1!
0"
0(
0&
#906
0!
1"
1(
1&
#907
1!
0"
0(
0&
#908
0!
1"
1(
1&
1%
#909
1!
0"
0(
0&
#910
0!
1"
1(
1&
#911
1!
0"
0(
0&
#912
0!
1"
1(
1&
0%
#913
1!
0"
0(
0&
#914
0!
1"
1(
1&
#915
1!
0"
0(
0&
#916
0!
1"
1(
1&
1%
#917
1!
0"
0(
0&
#918
0!
1"
1(
1&
#919
1!
0"
0(
0&
#920
0!
1"
1(
1&
0%
#921
1!
0"
0(
0&
#922
0!
1"
1(
1&
#923
1!
0"
0(
0&
#924
0!
1"
1(
1&
1%
#925
1!
0"
0(
0&
#926
0!
1"
1(
1&
#927
1!
0"
0(
0&
#928
0!
1"
1(
1&
0%
#929
1!
0"
0(
0&
#930
0!
1"
1(
1&
#931
1!
0"
0(
0&
#932
0!
1"
1(
1&
1%
