lab6/Tflipflop.v
module Tflipflop(q,q1,t,c);
output q,q1;
input t,c;
reg q,q1;
initial begin 
q=1'b1;
q1=1'b0;
end
always @ (c) begin
	if(c)
	begin
	if (t==1'b0) begin q=q; q1=q1; end
	else begin q=~q; q1=~q1; end
	end
	end
endmodule

lab6/Tflipfloptb.v
module Tflipfloptb;

wire q,q1;
reg t,c;

Tflipflop tf(.q(q), .q1(q1), .t(t), .c(c));

initial begin
c=1;
#10  t=0;
#10 t=0;
#10 t=1;
#10 t=1;
#50 $finish;
end

always begin
#10 c=~c;
end

initial begin
$dumpfile("Tflipflop.vcd");
$dumpvars(0,Tflipfloptb);
$monitor("time = %2d,  q=%b, q1=%b, t=%b, c=%b", $time,q,q1,t,c);
end

endmodule

lab6/Tflipflop.vcd
$date
	Thu Oct 25 16:36:05 2018
$end
$version
	Icarus Verilog
$end
$timescale
	1s
$end
$scope module Tflipfloptb $end
$var wire 1 ! q1 $end
$var wire 1 " q $end
$var reg 1 # c $end
$var reg 1 $ t $end
$scope module tf $end
$var wire 1 # c $end
$var wire 1 $ t $end
$var reg 1 " q $end
$var reg 1 ! q1 $end
$upscope $end
$upscope $end
$enddefinitions $end
#0
$dumpvars
x$
1#
0"
1!
$end
#10
0#
0$
#20
1#
#30
0#
1$
#40
0!
1"
1#
#50
0#
#60
1!
0"
1#
#70
0#
#80
0!
1"
1#
#90
0#
