not/not.v
module not_gate(input a, output result);

	supply1 Vdd;
	supply0 Gnd;

	pmos(result, Vdd, a);
	nmos(result, Gnd, a);

endmodule

nor/nor.v
module nor_gate(input a, input b, output result);

	wire c;
	supply1 Vdd;
	supply0 Gnd;

	pmos(c, Vdd, a);
	pmos(result, c, b);

	nmos(result, Gnd, a);
	nmos(result, Gnd, b);

endmodule

or/or.v
`include "../nor/nor.v"
// `include "../not/not.v"
module or_gate(input A, input B, output res);

	wire temp;
	nor_gate nand_temp(
		.a(A),
		.b(B),
		.result(temp)
	);
	not_gate not_temp(
		.a(temp),
		.result(res)
	);

endmodule

nand/nand.v
module nand_gate(input a, input b, output result);

	wire c;
	supply1 Vdd;
	supply0 Gnd;

	pmos(result, Vdd, a);
	pmos(result, Vdd, b);

	nmos(result, c, a);
	nmos(c, Gnd, b);

endmodule

and/and.v
`include "../nand/nand.v"
`include "../not/not.v"
module and_gate(input A, input B, output res);

	wire temp;
	nand_gate nand_temp(
		.a(A),
		.b(B),
		.result(temp)
	);
	not_gate not_temp(
		.a(temp),
		.result(res)
	);

endmodule

xor/xor.v
// `include "../not/not.v"
module xor_gate(input a, input b, output result);

	wire a_comp, b_comp;
	wire x,y;
	wire m;
	wire temp;

	supply0 Gnd;
	supply1 Vdd;

	not_gate not_temp1(
		.a(a),
		.result(a_comp)
	);

	not_gate not_temp2(
		.a(b),
		.result(b_comp)
	);

	nmos(x, Gnd, b);
	nmos(y, Gnd, b_comp);
	nmos(temp, x, a_comp);
	nmos(temp, y, a);

	pmos(m, Vdd, a);
	pmos(m, Vdd, b_comp);
	pmos(temp, m, a_comp);
	pmos(temp, m, b);

	not_gate not_temp3(
		.a(temp),
		.result(result)
	);

endmodule

half_adder/half_adder.v
`include "../xor/xor.v"
`include "../and/and.v"

module half_adder_self(input a, input b, output s, output c);

	xor_gate xor_temp(
		.a(a),
		.b(b), 
		.result(s)
	);
	and_gate and_temp(
		.A(a), 
		.B(b), 
		.res(c)
	);

endmodule

full_adder/full_adder.v
`include "../or/or.v"
`include "../half_adder/half_adder.v"

module full_adder(input a, input b, input cin, output s, output cout);

	wire half_adder_carry1, half_adder_carry2;
	wire half_adder_sum;

	half_adder_self half_adder_temp1(
		.a(a),
		.b(b),
		.s(half_adder_sum),
		.c(half_adder_carry1)
	);

	half_adder_self half_adder_temp2(
		.a(half_adder_sum),
		.b(cin),
		.s(s),
		.c(half_adder_carry2)
	);

	or_gate or_temp(
		.A(half_adder_carry1),
		.B(half_adder_carry2),
		.res(cout)
	);

endmodule

full_adder/full_adder_tb.v
module full_adder_tb();
reg abit;
reg bbit;
reg cbit;
wire s;
wire cout;

full_adder full_adder_tb(
	.a(abit),
	.b(bbit),
	.cin(cbit),
	.s(s),
	.cout(cout)
);

	initial
		begin
				 abit=0; bbit=0; cbit=0;
			#10; abit=0; bbit=0; cbit=1;
			#10; abit=0; bbit=1; cbit=0;
			#10; abit=0; bbit=1; cbit=1;
			#10; abit=1; bbit=0; cbit=0;
			#10; abit=1; bbit=0; cbit=1;
			#10; abit=1; bbit=1; cbit=0;
			#10; abit=1; bbit=1; cbit=1;
		end

	initial
		begin
			$dumpfile("full_adder.vcd");
			$dumpvars(0, full_adder_tb);
			$monitor("time = %2d, abit = %1b, bbit = %1b, cinbit = %1b, sum = %1b, cout = %1b", $time, abit, bbit, cbit, s, cout);
		end

endmodule

full_adder/full_adder.vcd
$date
	Thu Sep  6 15:45:02 2018
$end
$version
	Icarus Verilog
$end
$timescale
	1s
$end
$scope module full_adder_tb $end
$scope module full_adder_tb $end
$var wire 1 ! a $end
$var wire 1 " b $end
$var wire 1 # cin $end
$var wire 1 $ cout $end
$var wire 1 % half_adder_carry1 $end
$var wire 1 & half_adder_carry2 $end
$var wire 1 ' half_adder_sum $end
$var wire 1 ( s $end
$scope module half_adder_temp1 $end
$var wire 1 ! a $end
$var wire 1 " b $end
$var wire 1 % c $end
$var wire 1 ' s $end
$scope module and_temp $end
$var wire 1 ! A $end
$var wire 1 " B $end
$var wire 1 % res $end
$var wire 1 ) temp $end
$scope module nand_temp $end
$var wire 1 * Gnd $end
$var wire 1 + Vdd $end
$var wire 1 ! a $end
$var wire 1 " b $end
$var wire 1 , c $end
$var wire 1 ) result $end
$upscope $end
$scope module not_temp $end
$var wire 1 - Gnd $end
$var wire 1 . Vdd $end
$var wire 1 ) a $end
$var wire 1 % result $end
$upscope $end
$upscope $end
$scope module xor_temp $end
$var wire 1 / Gnd $end
$var wire 1 0 Vdd $end
$var wire 1 ! a $end
$var wire 1 1 a_comp $end
$var wire 1 " b $end
$var wire 1 2 b_comp $end
$var wire 1 3 m $end
$var wire 1 ' result $end
$var wire 1 4 temp $end
$var wire 1 5 x $end
$var wire 1 6 y $end
$scope module not_temp1 $end
$var wire 1 7 Gnd $end
$var wire 1 8 Vdd $end
$var wire 1 ! a $end
$var wire 1 1 result $end
$upscope $end
$scope module not_temp2 $end
$var wire 1 9 Gnd $end
$var wire 1 : Vdd $end
$var wire 1 " a $end
$var wire 1 2 result $end
$upscope $end
$scope module not_temp3 $end
$var wire 1 ; Gnd $end
$var wire 1 < Vdd $end
$var wire 1 4 a $end
$var wire 1 ' result $end
$upscope $end
$upscope $end
$upscope $end
$scope module half_adder_temp2 $end
$var wire 1 ' a $end
$var wire 1 # b $end
$var wire 1 & c $end
$var wire 1 ( s $end
$scope module and_temp $end
$var wire 1 ' A $end
$var wire 1 # B $end
$var wire 1 & res $end
$var wire 1 = temp $end
$scope module nand_temp $end
$var wire 1 > Gnd $end
$var wire 1 ? Vdd $end
$var wire 1 ' a $end
$var wire 1 # b $end
$var wire 1 @ c $end
$var wire 1 = result $end
$upscope $end
$scope module not_temp $end
$var wire 1 A Gnd $end
$var wire 1 B Vdd $end
$var wire 1 = a $end
$var wire 1 & result $end
$upscope $end
$upscope $end
$scope module xor_temp $end
$var wire 1 C Gnd $end
$var wire 1 D Vdd $end
$var wire 1 ' a $end
$var wire 1 E a_comp $end
$var wire 1 # b $end
$var wire 1 F b_comp $end
$var wire 1 G m $end
$var wire 1 ( result $end
$var wire 1 H temp $end
$var wire 1 I x $end
$var wire 1 J y $end
$scope module not_temp1 $end
$var wire 1 K Gnd $end
$var wire 1 L Vdd $end
$var wire 1 ' a $end
$var wire 1 E result $end
$upscope $end
$scope module not_temp2 $end
$var wire 1 M Gnd $end
$var wire 1 N Vdd $end
$var wire 1 # a $end
$var wire 1 F result $end
$upscope $end
$scope module not_temp3 $end
$var wire 1 O Gnd $end
$var wire 1 P Vdd $end
$var wire 1 H a $end
$var wire 1 ( result $end
$upscope $end
$upscope $end
$upscope $end
$scope module or_temp $end
$var wire 1 % A $end
$var wire 1 & B $end
$var wire 1 $ res $end
$var wire 1 Q temp $end
$scope module nand_temp $end
$var wire 1 R Gnd $end
$var wire 1 S Vdd $end
$var wire 1 % a $end
$var wire 1 & b $end
$var wire 1 T c $end
$var wire 1 Q result $end
$upscope $end
$scope module not_temp $end
$var wire 1 U Gnd $end
$var wire 1 V Vdd $end
$var wire 1 Q a $end
$var wire 1 $ result $end
$upscope $end
$upscope $end
$upscope $end
$upscope $end
$enddefinitions $end
#0
$dumpvars
1V
0U
1T
1S
0R
1Q
1P
0O
1N
0M
1L
0K
0J
zI
1H
1G
1F
1E
1D
0C
1B
0A
z@
1?
0>
1=
1<
0;
1:
09
18
07
06
z5
14
13
12
11
10
0/
1.
0-
z,
1+
0*
1)
0(
0'
0&
0%
0$
0#
0"
0!
$end
#10
0@
0I
1(
0H
zJ
0F
1#
#20
z@
zI
0J
zG
1F
0#
0,
05
0$
1Q
0&
1=
1(
0H
0E
1'
04
z6
02
1"
#30
1$
0Q
1&
0=
0@
0I
zJ
0(
1H
1G
0F
1#
#40
z@
zI
0J
zG
1F
0#
z,
z5
06
z3
12
0"
1T
0%
1)
0$
1Q
0&
1=
1(
0H
0E
1'
04
01
1!
#50
1$
0Q
1&
0=
0@
0I
zJ
0(
1H
1G
0F
1#
#60
z@
zI
0J
1F
0#
zT
1%
0)
0,
05
z6
1$
0Q
0&
1=
0(
1H
1E
0'
14
13
02
1"
#70
0@
0I
1(
0H
zJ
0F
1#
